{
"meta":{"test_sets":[],"test_metrics":[],"learn_metrics":[{"best_value":"Min","name":"RMSE"}],"launch_mode":"Train","parameters":"","iteration_count":1000,"learn_sets":["learn"],"name":"experiment"},
"iterations":[
{"learn":[14.59871775],"iteration":0,"passed_time":0.05655167443,"remaining_time":56.49512275},
{"learn":[14.22518863],"iteration":1,"passed_time":0.05691464966,"remaining_time":28.40041018},
{"learn":[13.8866124],"iteration":2,"passed_time":0.05725779063,"remaining_time":19.02867242},
{"learn":[13.52356875],"iteration":3,"passed_time":0.05766639299,"remaining_time":14.35893185},
{"learn":[13.18870211],"iteration":4,"passed_time":0.05803211835,"remaining_time":11.54839155},
{"learn":[12.9124226],"iteration":5,"passed_time":0.05837346757,"remaining_time":9.670537795},
{"learn":[12.60003351],"iteration":6,"passed_time":0.05868831556,"remaining_time":8.325356765},
{"learn":[12.32990573],"iteration":7,"passed_time":0.05900620536,"remaining_time":7.316769465},
{"learn":[12.0660619],"iteration":8,"passed_time":0.05932459519,"remaining_time":6.532297092},
{"learn":[11.77309809],"iteration":9,"passed_time":0.05960927511,"remaining_time":5.901318235},
{"learn":[11.49227636],"iteration":10,"passed_time":0.0599356653,"remaining_time":5.38876118},
{"learn":[11.26264833],"iteration":11,"passed_time":0.06023655431,"remaining_time":4.959476305},
{"learn":[11.04260393],"iteration":12,"passed_time":0.06054048513,"remaining_time":4.596419909},
{"learn":[10.79916926],"iteration":13,"passed_time":0.06084804111,"remaining_time":4.28544061},
{"learn":[10.5541002],"iteration":14,"passed_time":0.06115926393,"remaining_time":4.016124998},
{"learn":[10.31918115],"iteration":15,"passed_time":0.06143260999,"remaining_time":3.778105514},
{"learn":[10.10004441],"iteration":16,"passed_time":0.06169687229,"remaining_time":3.56753091},
{"learn":[9.894556723],"iteration":17,"passed_time":0.06198638577,"remaining_time":3.381701713},
{"learn":[9.690174082],"iteration":18,"passed_time":0.06233061013,"remaining_time":3.218227818},
{"learn":[9.506034866],"iteration":19,"passed_time":0.06268004307,"remaining_time":3.07132211},
{"learn":[9.338524633],"iteration":20,"passed_time":0.06303830974,"remaining_time":2.938785964},
{"learn":[9.170203312],"iteration":21,"passed_time":0.06335690791,"remaining_time":2.816502543},
{"learn":[9.010299969],"iteration":22,"passed_time":0.06372825853,"remaining_time":2.707065591},
{"learn":[8.843866678],"iteration":23,"passed_time":0.06405427371,"remaining_time":2.604873798},
{"learn":[8.690548059],"iteration":24,"passed_time":0.06439724801,"remaining_time":2.511492672},
{"learn":[8.555307687],"iteration":25,"passed_time":0.06467409423,"remaining_time":2.422791069},
{"learn":[8.413851302],"iteration":26,"passed_time":0.06498702547,"remaining_time":2.341939844},
{"learn":[8.29256019],"iteration":27,"passed_time":0.06531412403,"remaining_time":2.267333163},
{"learn":[8.162193833],"iteration":28,"passed_time":0.06560463755,"remaining_time":2.196624244},
{"learn":[8.040736294],"iteration":29,"passed_time":0.06589956795,"remaining_time":2.130752697},
{"learn":[7.921220278],"iteration":30,"passed_time":0.06617116393,"remaining_time":2.068382511},
{"learn":[7.809589039],"iteration":31,"passed_time":0.06644613506,"remaining_time":2.009995586},
{"learn":[7.699675801],"iteration":32,"passed_time":0.0667712752,"remaining_time":1.956600701},
{"learn":[7.60645267],"iteration":33,"passed_time":0.06708974836,"remaining_time":1.906138145},
{"learn":[7.498880302],"iteration":34,"passed_time":0.06733646818,"remaining_time":1.856562623},
{"learn":[7.401158744],"iteration":35,"passed_time":0.06761785628,"remaining_time":1.810655929},
{"learn":[7.306431077],"iteration":36,"passed_time":0.06795420527,"remaining_time":1.768645937},
{"learn":[7.223863468],"iteration":37,"passed_time":0.0682427187,"remaining_time":1.7276183},
{"learn":[7.143477682],"iteration":38,"passed_time":0.06863248685,"remaining_time":1.691174868},
{"learn":[7.062817131],"iteration":39,"passed_time":0.06892141697,"remaining_time":1.654114007},
{"learn":[6.990793435],"iteration":40,"passed_time":0.06924926556,"remaining_time":1.619757212},
{"learn":[6.931862224],"iteration":41,"passed_time":0.06954257088,"remaining_time":1.586232926},
{"learn":[6.858296558],"iteration":42,"passed_time":0.06991983845,"remaining_time":1.556122916},
{"learn":[6.786268161],"iteration":43,"passed_time":0.07022126915,"remaining_time":1.525716666},
{"learn":[6.717118549],"iteration":44,"passed_time":0.07049924042,"remaining_time":1.496150547},
{"learn":[6.652948106],"iteration":45,"passed_time":0.07087579962,"remaining_time":1.469902453},
{"learn":[6.589686076],"iteration":46,"passed_time":0.07133752945,"remaining_time":1.446482246},
{"learn":[6.531283097],"iteration":47,"passed_time":0.07238428651,"remaining_time":1.435621682},
{"learn":[6.471368031],"iteration":48,"passed_time":0.0727268858,"remaining_time":1.411495273},
{"learn":[6.416481395],"iteration":49,"passed_time":0.07298027259,"remaining_time":1.386625179},
{"learn":[6.369870822],"iteration":50,"passed_time":0.0732654942,"remaining_time":1.363312824},
{"learn":[6.325678067],"iteration":51,"passed_time":0.07361013525,"remaining_time":1.341969389},
{"learn":[6.275766122],"iteration":52,"passed_time":0.07388164789,"remaining_time":1.320111709},
{"learn":[6.224773967],"iteration":53,"passed_time":0.074184787,"remaining_time":1.299607565},
{"learn":[6.182249254],"iteration":54,"passed_time":0.07444863262,"remaining_time":1.27916287},
{"learn":[6.139904173],"iteration":55,"passed_time":0.07474864659,"remaining_time":1.260048614},
{"learn":[6.100525536],"iteration":56,"passed_time":0.07508237045,"remaining_time":1.242152199},
{"learn":[6.062568564],"iteration":57,"passed_time":0.07536509195,"remaining_time":1.224033045},
{"learn":[6.030559288],"iteration":58,"passed_time":0.0757163583,"remaining_time":1.207611749},
{"learn":[5.997931376],"iteration":59,"passed_time":0.07600124657,"remaining_time":1.190686196},
{"learn":[5.964103835],"iteration":60,"passed_time":0.07633259533,"remaining_time":1.175021426},
{"learn":[5.933729724],"iteration":61,"passed_time":0.07660656641,"remaining_time":1.158983214},
{"learn":[5.901932711],"iteration":62,"passed_time":0.07690162182,"remaining_time":1.143759042},
{"learn":[5.873727795],"iteration":63,"passed_time":0.07718367661,"remaining_time":1.12881127},
{"learn":[5.846485734],"iteration":64,"passed_time":0.0774884408,"remaining_time":1.114641418},
{"learn":[5.820630862],"iteration":65,"passed_time":0.07776674543,"remaining_time":1.100517276},
{"learn":[5.793646238],"iteration":66,"passed_time":0.07803571628,"remaining_time":1.086676467},
{"learn":[5.765388646],"iteration":67,"passed_time":0.07828114437,"remaining_time":1.072912155},
{"learn":[5.747073912],"iteration":68,"passed_time":0.07855169864,"remaining_time":1.059878716},
{"learn":[5.722315217],"iteration":69,"passed_time":0.07880875227,"remaining_time":1.047030566},
{"learn":[5.699970599],"iteration":70,"passed_time":0.07982646632,"remaining_time":1.044489961},
{"learn":[5.682732647],"iteration":71,"passed_time":0.08009002025,"remaining_time":1.032271372},
{"learn":[5.663525791],"iteration":72,"passed_time":0.08049420574,"remaining_time":1.022166147},
{"learn":[5.642381613],"iteration":73,"passed_time":0.08074971763,"remaining_time":1.010462683},
{"learn":[5.621404779],"iteration":74,"passed_time":0.08106614903,"remaining_time":0.999815838},
{"learn":[5.602460129],"iteration":75,"passed_time":0.08133107803,"remaining_time":0.9888146855},
{"learn":[5.587337574],"iteration":76,"passed_time":0.08161138275,"remaining_time":0.9782767049},
{"learn":[5.572393026],"iteration":77,"passed_time":0.08190177126,"remaining_time":0.9681209373},
{"learn":[5.558425806],"iteration":78,"passed_time":0.08219020136,"remaining_time":0.9581920943},
{"learn":[5.541518902],"iteration":79,"passed_time":0.08245858885,"remaining_time":0.9482737718},
{"learn":[5.526157283],"iteration":80,"passed_time":0.08274797733,"remaining_time":0.9388319897},
{"learn":[5.511746977],"iteration":81,"passed_time":0.08308415964,"remaining_time":0.9301372994},
{"learn":[5.504975022],"iteration":82,"passed_time":0.0833152954,"remaining_time":0.9204834444},
{"learn":[5.493980522],"iteration":83,"passed_time":0.08359593347,"remaining_time":0.9115937507},
{"learn":[5.480745463],"iteration":84,"passed_time":0.08387294637,"remaining_time":0.9028675991},
{"learn":[5.464052013],"iteration":85,"passed_time":0.08417033521,"remaining_time":0.8945544928},
{"learn":[5.449143727],"iteration":86,"passed_time":0.08445847363,"remaining_time":0.8863285795},
{"learn":[5.438255432],"iteration":87,"passed_time":0.08473356977,"remaining_time":0.8781479048},
{"learn":[5.425927931],"iteration":88,"passed_time":0.08501654127,"remaining_time":0.8702254955},
{"learn":[5.412331217],"iteration":89,"passed_time":0.08532443061,"remaining_time":0.8627247984},
{"learn":[5.400691499],"iteration":90,"passed_time":0.08566307137,"remaining_time":0.8556893613},
{"learn":[5.391618744],"iteration":91,"passed_time":0.08599687858,"remaining_time":0.8487518016},
{"learn":[5.380766572],"iteration":92,"passed_time":0.08649981866,"remaining_time":0.8436057583},
{"learn":[5.372207183],"iteration":93,"passed_time":0.08692225499,"remaining_time":0.8377825854},
{"learn":[5.362918837],"iteration":94,"passed_time":0.0872353529,"remaining_time":0.8310315198},
{"learn":[5.348292324],"iteration":95,"passed_time":0.08752761651,"remaining_time":0.8242183888},
{"learn":[5.339772295],"iteration":96,"passed_time":0.08782367196,"remaining_time":0.817575008},
{"learn":[5.331515983],"iteration":97,"passed_time":0.08813051958,"remaining_time":0.8111604965},
{"learn":[5.323861644],"iteration":98,"passed_time":0.08837407258,"remaining_time":0.8042933272},
{"learn":[5.313277281],"iteration":99,"passed_time":0.08861916733,"remaining_time":0.7975725059},
{"learn":[5.30685627],"iteration":100,"passed_time":0.08889026328,"remaining_time":0.7912113534},
{"learn":[5.29652059],"iteration":101,"passed_time":0.08916848457,"remaining_time":0.7850323445},
{"learn":[5.288350766],"iteration":102,"passed_time":0.08947904069,"remaining_time":0.7792495097},
{"learn":[5.27993346],"iteration":103,"passed_time":0.0897985139,"remaining_time":0.7736487351},
{"learn":[5.271789139],"iteration":104,"passed_time":0.09008006867,"remaining_time":0.7678253472},
{"learn":[5.262684686],"iteration":105,"passed_time":0.0904580446,"remaining_time":0.7629197347},
{"learn":[5.251619772],"iteration":106,"passed_time":0.0907824347,"remaining_time":0.7576515345},
{"learn":[5.241012171],"iteration":107,"passed_time":0.09112070045,"remaining_time":0.7525894889},
{"learn":[5.232684032],"iteration":108,"passed_time":0.0915555957,"remaining_time":0.7484039979},
{"learn":[5.224267141],"iteration":109,"passed_time":0.09187715233,"remaining_time":0.7433696871},
{"learn":[5.216324968],"iteration":110,"passed_time":0.09231117254,"remaining_time":0.7393210125},
{"learn":[5.211102527],"iteration":111,"passed_time":0.09256051748,"remaining_time":0.7338726743},
{"learn":[5.206364257],"iteration":112,"passed_time":0.09278677802,"remaining_time":0.7283351513},
{"learn":[5.196937641],"iteration":113,"passed_time":0.09300082965,"remaining_time":0.7227959216},
{"learn":[5.190746047],"iteration":114,"passed_time":0.09334759579,"remaining_time":0.7183706285},
{"learn":[5.181885213],"iteration":115,"passed_time":0.09369682038,"remaining_time":0.7140343898},
{"learn":[5.178293568],"iteration":116,"passed_time":0.09390333,"remaining_time":0.7086892341},
{"learn":[5.170991438],"iteration":117,"passed_time":0.09413721589,"remaining_time":0.7036358001},
{"learn":[5.166257212],"iteration":118,"passed_time":0.0943738519,"remaining_time":0.6986837271},
{"learn":[5.161421246],"iteration":119,"passed_time":0.09464290609,"remaining_time":0.694047978},
{"learn":[5.158223542],"iteration":120,"passed_time":0.09489645957,"remaining_time":0.6893718013},
{"learn":[5.15470988],"iteration":121,"passed_time":0.09508296825,"remaining_time":0.6842856239},
{"learn":[5.146388143],"iteration":122,"passed_time":0.09532277108,"remaining_time":0.6796591076},
{"learn":[5.139529364],"iteration":123,"passed_time":0.09564853624,"remaining_time":0.675710627},
{"learn":[5.134276023],"iteration":124,"passed_time":0.09593442455,"remaining_time":0.6715409719},
{"learn":[5.128536065],"iteration":125,"passed_time":0.09621518763,"remaining_time":0.6673974126},
{"learn":[5.123300353],"iteration":126,"passed_time":0.09640252968,"remaining_time":0.6626725072},
{"learn":[5.116200518],"iteration":127,"passed_time":0.09664279087,"remaining_time":0.6583790128},
{"learn":[5.108728704],"iteration":128,"passed_time":0.0970515599,"remaining_time":0.6552861137},
{"learn":[5.104075866],"iteration":129,"passed_time":0.09732536431,"remaining_time":0.6513312842},
{"learn":[5.100317606],"iteration":130,"passed_time":0.09763704549,"remaining_time":0.6476839124},
{"learn":[5.095814182],"iteration":131,"passed_time":0.09792272545,"remaining_time":0.6439161037},
{"learn":[5.092146915],"iteration":132,"passed_time":0.09816823688,"remaining_time":0.6399388073},
{"learn":[5.085258329],"iteration":133,"passed_time":0.09844408306,"remaining_time":0.6362132532},
{"learn":[5.079219421],"iteration":134,"passed_time":0.09868355254,"remaining_time":0.6323057255},
{"learn":[5.076476829],"iteration":135,"passed_time":0.09890797965,"remaining_time":0.6283565766},
{"learn":[5.072133867],"iteration":136,"passed_time":0.0992475788,"remaining_time":0.6251873029},
{"learn":[5.067031564],"iteration":137,"passed_time":0.09950963266,"remaining_time":0.621574662},
{"learn":[5.061358312],"iteration":138,"passed_time":0.09979939615,"remaining_time":0.6181818711},
{"learn":[5.056759124],"iteration":139,"passed_time":0.1001452873,"remaining_time":0.6151781932},
{"learn":[5.050254],"iteration":140,"passed_time":0.1004499264,"remaining_time":0.6119608994},
{"learn":[5.048376474],"iteration":141,"passed_time":0.1005803908,"remaining_time":0.6077322208},
{"learn":[5.042603751],"iteration":142,"passed_time":0.100913573,"remaining_time":0.6047757488},
{"learn":[5.037477349],"iteration":143,"passed_time":0.1012684645,"remaining_time":0.6019847615},
{"learn":[5.03230489],"iteration":144,"passed_time":0.1016266479,"remaining_time":0.5992467858},
{"learn":[5.025976187],"iteration":145,"passed_time":0.1019856646,"remaining_time":0.5965462847},
{"learn":[5.01952451],"iteration":146,"passed_time":0.102301221,"remaining_time":0.5936254522},
{"learn":[5.017569424],"iteration":147,"passed_time":0.1025584829,"remaining_time":0.5904042396},
{"learn":[5.008962367],"iteration":148,"passed_time":0.1028068695,"remaining_time":0.5871721204},
{"learn":[5.003880266],"iteration":149,"passed_time":0.1031241343,"remaining_time":0.5843700942},
{"learn":[4.996387564],"iteration":150,"passed_time":0.1034391073,"remaining_time":0.5815880932},
{"learn":[4.993361683],"iteration":151,"passed_time":0.1036826186,"remaining_time":0.5784398722},
{"learn":[4.99005752],"iteration":152,"passed_time":0.103919588,"remaining_time":0.5752934053},
{"learn":[4.986908764],"iteration":153,"passed_time":0.1041815168,"remaining_time":0.5723218392},
{"learn":[4.985207175],"iteration":154,"passed_time":0.1044264866,"remaining_time":0.5692927816},
{"learn":[4.979003494],"iteration":155,"passed_time":0.1046806234,"remaining_time":0.5663490138},
{"learn":[4.973142217],"iteration":156,"passed_time":0.1049468441,"remaining_time":0.5635043923},
{"learn":[4.967056696],"iteration":157,"passed_time":0.1052460664,"remaining_time":0.5608682779},
{"learn":[4.961460696],"iteration":158,"passed_time":0.1055723732,"remaining_time":0.558404817},
{"learn":[4.954240363],"iteration":159,"passed_time":0.1058115927,"remaining_time":0.5555108618},
{"learn":[4.952320707],"iteration":160,"passed_time":0.10593264,"remaining_time":0.5520340682},
{"learn":[4.948337777],"iteration":161,"passed_time":0.1061727762,"remaining_time":0.5492147312},
{"learn":[4.943228639],"iteration":162,"passed_time":0.106426163,"remaining_time":0.5464950824},
{"learn":[4.938545759],"iteration":163,"passed_time":0.1066815499,"remaining_time":0.5438157055},
{"learn":[4.935330572],"iteration":164,"passed_time":0.1069237695,"remaining_time":0.5410990759},
{"learn":[4.932051543],"iteration":165,"passed_time":0.1072282003,"remaining_time":0.5387248137},
{"learn":[4.928964153],"iteration":166,"passed_time":0.1074806704,"remaining_time":0.5361161585},
{"learn":[4.922860227],"iteration":167,"passed_time":0.1078797723,"remaining_time":0.5342617297},
{"learn":[4.917668772],"iteration":168,"passed_time":0.1081111581,"remaining_time":0.5315998366},
{"learn":[4.910365386],"iteration":169,"passed_time":0.108345669,"remaining_time":0.5289817958},
{"learn":[4.906457206],"iteration":170,"passed_time":0.1085768465,"remaining_time":0.526375472},
{"learn":[4.901996508],"iteration":171,"passed_time":0.1088424838,"remaining_time":0.5239626547},
{"learn":[4.896816173],"iteration":172,"passed_time":0.1091449146,"remaining_time":0.5217505454},
{"learn":[4.891123132],"iteration":173,"passed_time":0.1094214691,"remaining_time":0.5194375488},
{"learn":[4.887630202],"iteration":174,"passed_time":0.1097080241,"remaining_time":0.5171949708},
{"learn":[4.885259712],"iteration":175,"passed_time":0.109970328,"remaining_time":0.5148610811},
{"learn":[4.880659728],"iteration":176,"passed_time":0.1102321318,"remaining_time":0.5125482741},
{"learn":[4.877299723],"iteration":177,"passed_time":0.1104879771,"remaining_time":0.5102309953},
{"learn":[4.874038772],"iteration":178,"passed_time":0.1107259048,"remaining_time":0.5078545691},
{"learn":[4.86943698],"iteration":179,"passed_time":0.1109785416,"remaining_time":0.5055689117},
{"learn":[4.861268711],"iteration":180,"passed_time":0.1112920145,"remaining_time":0.5035809939},
{"learn":[4.858673056],"iteration":181,"passed_time":0.1115772778,"remaining_time":0.5014846882},
{"learn":[4.854036207],"iteration":182,"passed_time":0.1118502072,"remaining_time":0.4993531107},
{"learn":[4.85130244],"iteration":183,"passed_time":0.1121270117,"remaining_time":0.4972589216},
{"learn":[4.847510084],"iteration":184,"passed_time":0.1124210254,"remaining_time":0.4952601931},
{"learn":[4.845691673],"iteration":185,"passed_time":0.1126755373,"remaining_time":0.4931069212},
{"learn":[4.842058646],"iteration":186,"passed_time":0.1129091315,"remaining_time":0.4908830155},
{"learn":[4.838623675],"iteration":187,"passed_time":0.1131651434,"remaining_time":0.4887771087},
{"learn":[4.834602161],"iteration":188,"passed_time":0.1134473232,"remaining_time":0.4868030641},
{"learn":[4.830858976],"iteration":189,"passed_time":0.1137005433,"remaining_time":0.4847233689},
{"learn":[4.827590511],"iteration":190,"passed_time":0.1139735977,"remaining_time":0.4827468091},
{"learn":[4.822246226],"iteration":191,"passed_time":0.1142637779,"remaining_time":0.4808600652},
{"learn":[4.816686395],"iteration":192,"passed_time":0.1145653336,"remaining_time":0.4790374311},
{"learn":[4.814797121],"iteration":193,"passed_time":0.1148556804,"remaining_time":0.4771839094},
{"learn":[4.811639392],"iteration":194,"passed_time":0.1151321516,"remaining_time":0.4752891388},
{"learn":[4.804813432],"iteration":195,"passed_time":0.1154075811,"remaining_time":0.4734066083},
{"learn":[4.80251613],"iteration":196,"passed_time":0.1156709684,"remaining_time":0.4714913077},
{"learn":[4.800087884],"iteration":197,"passed_time":0.1159012291,"remaining_time":0.4694585139},
{"learn":[4.794773135],"iteration":198,"passed_time":0.1162192856,"remaining_time":0.4677972249},
{"learn":[4.791664833],"iteration":199,"passed_time":0.1165445507,"remaining_time":0.4661782029},
{"learn":[4.785989873],"iteration":200,"passed_time":0.1167867287,"remaining_time":0.4642417722},
{"learn":[4.782387142],"iteration":201,"passed_time":0.1169999886,"remaining_time":0.4622078757},
{"learn":[4.778623704],"iteration":202,"passed_time":0.1172357912,"remaining_time":0.4602804218},
{"learn":[4.775772178],"iteration":203,"passed_time":0.117452468,"remaining_time":0.4582949241},
{"learn":[4.77023101],"iteration":204,"passed_time":0.1176909791,"remaining_time":0.456411358},
{"learn":[4.764496689],"iteration":205,"passed_time":0.1179991184,"remaining_time":0.4548121361},
{"learn":[4.763138716],"iteration":206,"passed_time":0.1182647975,"remaining_time":0.4530627266},
{"learn":[4.758053283],"iteration":207,"passed_time":0.1185569361,"remaining_time":0.4514283335},
{"learn":[4.755063788],"iteration":208,"passed_time":0.1188557417,"remaining_time":0.4498320175},
{"learn":[4.752465267],"iteration":209,"passed_time":0.1192598855,"remaining_time":0.4486443311},
{"learn":[4.748067377],"iteration":210,"passed_time":0.1195810254,"remaining_time":0.4471536922},
{"learn":[4.744163298],"iteration":211,"passed_time":0.1198470795,"remaining_time":0.4454693331},
{"learn":[4.736670896],"iteration":212,"passed_time":0.1201659693,"remaining_time":0.4439935111},
{"learn":[4.73349255],"iteration":213,"passed_time":0.1204147309,"remaining_time":0.4422709275},
{"learn":[4.731864595],"iteration":214,"passed_time":0.1206471167,"remaining_time":0.4405022634},
{"learn":[4.728398311],"iteration":215,"passed_time":0.1209330884,"remaining_time":0.4389423207},
{"learn":[4.723865975],"iteration":216,"passed_time":0.1211983507,"remaining_time":0.4373193945},
{"learn":[4.723483365],"iteration":217,"passed_time":0.1214713634,"remaining_time":0.4357367257},
{"learn":[4.72095416],"iteration":218,"passed_time":0.1217581268,"remaining_time":0.4342150548},
{"learn":[4.716173382],"iteration":219,"passed_time":0.122006305,"remaining_time":0.4325678086},
{"learn":[4.710563974],"iteration":220,"passed_time":0.1223096108,"remaining_time":0.4311275421},
{"learn":[4.707160263],"iteration":221,"passed_time":0.1226417929,"remaining_time":0.4297987157},
{"learn":[4.70408351],"iteration":222,"passed_time":0.1230110184,"remaining_time":0.4286078983},
{"learn":[4.702501831],"iteration":223,"passed_time":0.1233570762,"remaining_time":0.4273441569},
{"learn":[4.700269738],"iteration":224,"passed_time":0.1236602153,"remaining_time":0.4259407417},
{"learn":[4.695346302],"iteration":225,"passed_time":0.1239349364,"remaining_time":0.4244497381},
{"learn":[4.689769299],"iteration":226,"passed_time":0.1242280751,"remaining_time":0.4230321676},
{"learn":[4.687919514],"iteration":227,"passed_time":0.1245861751,"remaining_time":0.4218444174},
{"learn":[4.682982074],"iteration":228,"passed_time":0.125027529,"remaining_time":0.4209442133},
{"learn":[4.679578702],"iteration":229,"passed_time":0.1255290107,"remaining_time":0.4202492966},
{"learn":[4.675751423],"iteration":230,"passed_time":0.1259155703,"remaining_time":0.4191734787},
{"learn":[4.672710726],"iteration":231,"passed_time":0.1268911574,"remaining_time":0.4200534866},
{"learn":[4.6690533],"iteration":232,"passed_time":0.1279365394,"remaining_time":0.4211473207},
{"learn":[4.667595702],"iteration":233,"passed_time":0.1282391785,"remaining_time":0.4197914989},
{"learn":[4.664241291],"iteration":234,"passed_time":0.1284945654,"remaining_time":0.4182908192},
{"learn":[4.662246999],"iteration":235,"passed_time":0.1287766202,"remaining_time":0.4168870247},
{"learn":[4.658668443],"iteration":236,"passed_time":0.1290135896,"remaining_time":0.4153475478},
{"learn":[4.658017572],"iteration":237,"passed_time":0.1293116451,"remaining_time":0.4140145948},
{"learn":[4.657656705],"iteration":238,"passed_time":0.1296479108,"remaining_time":0.4128119669},
{"learn":[4.653242871],"iteration":239,"passed_time":0.1298843801,"remaining_time":0.411300537},
{"learn":[4.6507302],"iteration":240,"passed_time":0.1302452302,"remaining_time":0.4101914097},
{"learn":[4.647671336],"iteration":241,"passed_time":0.1305020338,"remaining_time":0.4087625688},
{"learn":[4.645506007],"iteration":242,"passed_time":0.1307515455,"remaining_time":0.4073206581},
{"learn":[4.641297906],"iteration":243,"passed_time":0.1309862647,"remaining_time":0.4058426891},
{"learn":[4.63798107],"iteration":244,"passed_time":0.1312599025,"remaining_time":0.4044948015},
{"learn":[4.635062318],"iteration":245,"passed_time":0.1314717457,"remaining_time":0.4029662448},
{"learn":[4.631606017],"iteration":246,"passed_time":0.1317631759,"remaining_time":0.4016909775},
{"learn":[4.630215494],"iteration":247,"passed_time":0.1320676484,"remaining_time":0.4004631919},
{"learn":[4.62729814],"iteration":248,"passed_time":0.1323574536,"remaining_time":0.3991985848},
{"learn":[4.624691756],"iteration":249,"passed_time":0.1326959693,"remaining_time":0.398087908},
{"learn":[4.621840053],"iteration":250,"passed_time":0.1329737323,"remaining_time":0.3968020934},
{"learn":[4.619602091],"iteration":251,"passed_time":0.1332293275,"remaining_time":0.39545848},
{"learn":[4.613584029],"iteration":252,"passed_time":0.1335598845,"remaining_time":0.3943447974},
{"learn":[4.6119388],"iteration":253,"passed_time":0.1338272303,"remaining_time":0.3930516292},
{"learn":[4.60870702],"iteration":254,"passed_time":0.1340876591,"remaining_time":0.3917462982},
{"learn":[4.604771557],"iteration":255,"passed_time":0.1344319668,"remaining_time":0.3906929035},
{"learn":[4.604231277],"iteration":256,"passed_time":0.1347292723,"remaining_time":0.3895091414},
{"learn":[4.600750354],"iteration":257,"passed_time":0.1350050768,"remaining_time":0.3882704147},
{"learn":[4.596488253],"iteration":258,"passed_time":0.1352742143,"remaining_time":0.3870200495},
{"learn":[4.59470784],"iteration":259,"passed_time":0.1355771868,"remaining_time":0.3858735316},
{"learn":[4.588818005],"iteration":260,"passed_time":0.1358549914,"remaining_time":0.384662217},
{"learn":[4.585054174],"iteration":261,"passed_time":0.136204091,"remaining_time":0.3836588517},
{"learn":[4.581471435],"iteration":262,"passed_time":0.1364698533,"remaining_time":0.3824269274},
{"learn":[4.577555199],"iteration":263,"passed_time":0.1367451995,"remaining_time":0.381229041},
{"learn":[4.57457145],"iteration":264,"passed_time":0.13704163,"remaining_time":0.3800965963},
{"learn":[4.573029224],"iteration":265,"passed_time":0.1373974382,"remaining_time":0.3791342843},
{"learn":[4.571326203],"iteration":266,"passed_time":0.1377309954,"remaining_time":0.3781154293},
{"learn":[4.571019224],"iteration":267,"passed_time":0.1386268704,"remaining_time":0.3786375715},
{"learn":[4.565766631],"iteration":268,"passed_time":0.1389084252,"remaining_time":0.3774797726},
{"learn":[4.563383471],"iteration":269,"passed_time":0.1391812296,"remaining_time":0.3763048059},
{"learn":[4.558165805],"iteration":270,"passed_time":0.1394309079,"remaining_time":0.3750742872},
{"learn":[4.55629209],"iteration":271,"passed_time":0.1396990037,"remaining_time":0.3739002745},
{"learn":[4.549383848],"iteration":272,"passed_time":0.1399911006,"remaining_time":0.3727968137},
{"learn":[4.546227503],"iteration":273,"passed_time":0.1403333665,"remaining_time":0.3718322048},
{"learn":[4.540620977],"iteration":274,"passed_time":0.140650173,"remaining_time":0.3708050014},
{"learn":[4.532898237],"iteration":275,"passed_time":0.1409098934,"remaining_time":0.3696331986},
{"learn":[4.529757367],"iteration":276,"passed_time":0.1411619468,"remaining_time":0.3684479694},
{"learn":[4.52579294],"iteration":277,"passed_time":0.1414095,"remaining_time":0.3672577661},
{"learn":[4.521572155],"iteration":278,"passed_time":0.1416872212,"remaining_time":0.3661522814},
{"learn":[4.518818099],"iteration":279,"passed_time":0.141925899,"remaining_time":0.3649523118},
{"learn":[4.514012334],"iteration":280,"passed_time":0.1421967033,"remaining_time":0.3638413867},
{"learn":[4.508331416],"iteration":281,"passed_time":0.1424279641,"remaining_time":0.3626357383},
{"learn":[4.506038537],"iteration":282,"passed_time":0.1427449371,"remaining_time":0.361654134},
{"learn":[4.505805643],"iteration":283,"passed_time":0.1430212417,"remaining_time":0.3605746797},
{"learn":[4.501550352],"iteration":284,"passed_time":0.1432666281,"remaining_time":0.3594232951},
{"learn":[4.494692643],"iteration":285,"passed_time":0.1435377657,"remaining_time":0.358342534},
{"learn":[4.489330245],"iteration":286,"passed_time":0.143787319,"remaining_time":0.3572137925},
{"learn":[4.484826955],"iteration":287,"passed_time":0.1440862079,"remaining_time":0.3562131251},
{"learn":[4.478285428],"iteration":288,"passed_time":0.1443657626,"remaining_time":0.3551697481},
{"learn":[4.475311671],"iteration":289,"passed_time":0.1446026903,"remaining_time":0.3540272763},
{"learn":[4.471581298],"iteration":290,"passed_time":0.1448484101,"remaining_time":0.3529124493},
{"learn":[4.469164956],"iteration":291,"passed_time":0.1450937132,"remaining_time":0.3518025648},
{"learn":[4.462068024],"iteration":292,"passed_time":0.14538356,"remaining_time":0.3508060645},
{"learn":[4.458540976],"iteration":293,"passed_time":0.1456537392,"remaining_time":0.3497671425},
{"learn":[4.455757458],"iteration":294,"passed_time":0.1459146264,"remaining_time":0.3487112258},
{"learn":[4.453027414],"iteration":295,"passed_time":0.1461445954,"remaining_time":0.3475871459},
{"learn":[4.450659338],"iteration":296,"passed_time":0.146401024,"remaining_time":0.3465317168},
{"learn":[4.444696901],"iteration":297,"passed_time":0.1466784953,"remaining_time":0.3455312204},
{"learn":[4.442052813],"iteration":298,"passed_time":0.1469684254,"remaining_time":0.34456477},
{"learn":[4.440036756],"iteration":299,"passed_time":0.1472681061,"remaining_time":0.3436255808},
{"learn":[4.435017051],"iteration":300,"passed_time":0.1475515359,"remaining_time":0.3426529023},
{"learn":[4.429962125],"iteration":301,"passed_time":0.147846508,"remaining_time":0.3417114655},
{"learn":[4.427666256],"iteration":302,"passed_time":0.14817569,"remaining_time":0.3408529898},
{"learn":[4.425030004],"iteration":303,"passed_time":0.1484639117,"remaining_time":0.339904219},
{"learn":[4.422588771],"iteration":304,"passed_time":0.1487656341,"remaining_time":0.3389905433},
{"learn":[4.418936667],"iteration":305,"passed_time":0.1490505224,"remaining_time":0.338042688},
{"learn":[4.416887976],"iteration":306,"passed_time":0.1492999506,"remaining_time":0.3370191068},
{"learn":[4.413773354],"iteration":307,"passed_time":0.1495315448,"remaining_time":0.3359604837},
{"learn":[4.411129391],"iteration":308,"passed_time":0.1497448047,"remaining_time":0.3348662137},
{"learn":[4.40850819],"iteration":309,"passed_time":0.1500009833,"remaining_time":0.3338731563},
{"learn":[4.404880292],"iteration":310,"passed_time":0.150216785,"remaining_time":0.3327953854},
{"learn":[4.404593827],"iteration":311,"passed_time":0.1505278828,"remaining_time":0.3319332801},
{"learn":[4.402139942],"iteration":312,"passed_time":0.150789645,"remaining_time":0.3309664093},
{"learn":[4.400284725],"iteration":313,"passed_time":0.1510544073,"remaining_time":0.3300105842},
{"learn":[4.395805521],"iteration":314,"passed_time":0.1513184613,"remaining_time":0.3290576063},
{"learn":[4.392838833],"iteration":315,"passed_time":0.1516439348,"remaining_time":0.3282419348},
{"learn":[4.389213061],"iteration":316,"passed_time":0.1518679035,"remaining_time":0.3272106565},
{"learn":[4.3861981],"iteration":317,"passed_time":0.1521190819,"remaining_time":0.3262428109},
{"learn":[4.385054234],"iteration":318,"passed_time":0.1524014284,"remaining_time":0.325345996},
{"learn":[4.379364607],"iteration":319,"passed_time":0.1527169014,"remaining_time":0.3245234155},
{"learn":[4.378387619],"iteration":320,"passed_time":0.1529844972,"remaining_time":0.3236027215},
{"learn":[4.375816727],"iteration":321,"passed_time":0.1532455093,"remaining_time":0.3226722215},
{"learn":[4.374600202],"iteration":322,"passed_time":0.153545565,"remaining_time":0.3218277012},
{"learn":[4.37098897],"iteration":323,"passed_time":0.1538204944,"remaining_time":0.320934118},
{"learn":[4.367418484],"iteration":324,"passed_time":0.1540635474,"remaining_time":0.3199781369},
{"learn":[4.363584638],"iteration":325,"passed_time":0.1543556444,"remaining_time":0.3191279273},
{"learn":[4.360770706],"iteration":326,"passed_time":0.1545935304,"remaining_time":0.3181695596},
{"learn":[4.358675808],"iteration":327,"passed_time":0.1548527092,"remaining_time":0.317259209},
{"learn":[4.354228195],"iteration":328,"passed_time":0.1551083461,"remaining_time":0.3163455933},
{"learn":[4.353773425],"iteration":329,"passed_time":0.155378567,"remaining_time":0.3154655754},
{"learn":[4.351648009],"iteration":330,"passed_time":0.1556565799,"remaining_time":0.3146049908},
{"learn":[4.348209927],"iteration":331,"passed_time":0.1559075083,"remaining_time":0.3136934202},
{"learn":[4.345852733],"iteration":332,"passed_time":0.1561451443,"remaining_time":0.312759193},
{"learn":[4.34237339],"iteration":333,"passed_time":0.1565228702,"remaining_time":0.3121084778},
{"learn":[4.340814362],"iteration":334,"passed_time":0.1567682567,"remaining_time":0.3111966886},
{"learn":[4.339707068],"iteration":335,"passed_time":0.1570348941,"remaining_time":0.3103308621},
{"learn":[4.335430786],"iteration":336,"passed_time":0.1572752386,"remaining_time":0.3094168641},
{"learn":[4.33521887],"iteration":337,"passed_time":0.157583753,"remaining_time":0.3086403682},
{"learn":[4.328507238],"iteration":338,"passed_time":0.1578364731,"remaining_time":0.3077578428},
{"learn":[4.326140732],"iteration":339,"passed_time":0.158107694,"remaining_time":0.3069149355},
{"learn":[4.323785636],"iteration":340,"passed_time":0.1583889988,"remaining_time":0.3060948686},
{"learn":[4.320632534],"iteration":341,"passed_time":0.1587419319,"remaining_time":0.3054157637},
{"learn":[4.31973724],"iteration":342,"passed_time":0.1590051525,"remaining_time":0.3045667206},
{"learn":[4.318000924],"iteration":343,"passed_time":0.159244872,"remaining_time":0.3036762675},
{"learn":[4.312713628],"iteration":344,"passed_time":0.1594804246,"remaining_time":0.3027816757},
{"learn":[4.308220789],"iteration":345,"passed_time":0.1597421451,"remaining_time":0.3019403552},
{"learn":[4.305890947],"iteration":346,"passed_time":0.1599991988,"remaining_time":0.301093593},
{"learn":[4.305137856],"iteration":347,"passed_time":0.1602821703,"remaining_time":0.3002987788},
{"learn":[4.304787172],"iteration":348,"passed_time":0.160578059,"remaining_time":0.2995309926},
{"learn":[4.30350134],"iteration":349,"passed_time":0.1608389878,"remaining_time":0.2987009774},
{"learn":[4.30293809],"iteration":350,"passed_time":0.1610690819,"remaining_time":0.2978171913},
{"learn":[4.299548459],"iteration":351,"passed_time":0.1613065513,"remaining_time":0.2969506967},
{"learn":[4.294768408],"iteration":352,"passed_time":0.161550896,"remaining_time":0.2961003674},
{"learn":[4.294581479],"iteration":353,"passed_time":0.1618104497,"remaining_time":0.2952812162},
{"learn":[4.292551604],"iteration":354,"passed_time":0.1621373816,"remaining_time":0.294587637},
{"learn":[4.288628894],"iteration":355,"passed_time":0.162431187,"remaining_time":0.2938361922},
{"learn":[4.287802767],"iteration":356,"passed_time":0.1627125751,"remaining_time":0.2930649461},
{"learn":[4.284566905],"iteration":357,"passed_time":0.1630167559,"remaining_time":0.2923373109},
{"learn":[4.27890232],"iteration":358,"passed_time":0.1632791848,"remaining_time":0.2915374859},
{"learn":[4.276938023],"iteration":359,"passed_time":0.1635517808,"remaining_time":0.2907587214},
{"learn":[4.273425094],"iteration":360,"passed_time":0.163798584,"remaining_time":0.2899371057},
{"learn":[4.269726505],"iteration":361,"passed_time":0.1640444704,"remaining_time":0.2891170501},
{"learn":[4.265565857],"iteration":362,"passed_time":0.1643118579,"remaining_time":0.2883378883},
{"learn":[4.262117173],"iteration":363,"passed_time":0.1645737451,"remaining_time":0.2875519282},
{"learn":[4.259185148],"iteration":364,"passed_time":0.1648321321,"remaining_time":0.2867627503},
{"learn":[4.257668507],"iteration":365,"passed_time":0.1650886857,"remaining_time":0.2859732971},
{"learn":[4.253432436],"iteration":366,"passed_time":0.1653573649,"remaining_time":0.285207662},
{"learn":[4.250216667],"iteration":367,"passed_time":0.1656604206,"remaining_time":0.2845037659},
{"learn":[4.24514828],"iteration":368,"passed_time":0.1659747269,"remaining_time":0.283821281},
{"learn":[4.244015772],"iteration":369,"passed_time":0.1662272387,"remaining_time":0.2830355686},
{"learn":[4.240329192],"iteration":370,"passed_time":0.1665158771,"remaining_time":0.2823139804},
{"learn":[4.236718014],"iteration":371,"passed_time":0.1668151411,"remaining_time":0.2816126575},
{"learn":[4.233495944],"iteration":372,"passed_time":0.1670700279,"remaining_time":0.2808388941},
{"learn":[4.230357491],"iteration":373,"passed_time":0.1673222897,"remaining_time":0.2800635116},
{"learn":[4.227381215],"iteration":374,"passed_time":0.1675633009,"remaining_time":0.2792721682},
{"learn":[4.226169067],"iteration":375,"passed_time":0.1679064002,"remaining_time":0.2786531748},
{"learn":[4.225963861],"iteration":376,"passed_time":0.1682154563,"remaining_time":0.2779793879},
{"learn":[4.224346548],"iteration":377,"passed_time":0.1685406797,"remaining_time":0.2773341344},
{"learn":[4.222595381],"iteration":378,"passed_time":0.1688099006,"remaining_time":0.2765988081},
{"learn":[4.219700938],"iteration":379,"passed_time":0.169090622,"remaining_time":0.2758846991},
{"learn":[4.216356207],"iteration":380,"passed_time":0.1693325916,"remaining_time":0.275109906},
{"learn":[4.214326494],"iteration":381,"passed_time":0.1696176465,"remaining_time":0.2744076062},
{"learn":[4.212901398],"iteration":382,"passed_time":0.16987095,"remaining_time":0.2736563346},
{"learn":[4.211331091],"iteration":383,"passed_time":0.1701211283,"remaining_time":0.2729026433},
{"learn":[4.208624791],"iteration":384,"passed_time":0.1703725567,"remaining_time":0.2721535646},
{"learn":[4.204659106],"iteration":385,"passed_time":0.1706404442,"remaining_time":0.2714332454},
{"learn":[4.202968852],"iteration":386,"passed_time":0.1709461251,"remaining_time":0.2707751283},
{"learn":[4.197261935],"iteration":387,"passed_time":0.1712570145,"remaining_time":0.2701270435},
{"learn":[4.196934403],"iteration":388,"passed_time":0.1716414074,"remaining_time":0.2695961438},
{"learn":[4.192479929],"iteration":389,"passed_time":0.1719234622,"remaining_time":0.2689059281},
{"learn":[4.190243116],"iteration":390,"passed_time":0.1721729738,"remaining_time":0.2681671127},
{"learn":[4.185852431],"iteration":391,"passed_time":0.1724425281,"remaining_time":0.2674618802},
{"learn":[4.180967944],"iteration":392,"passed_time":0.1727033735,"remaining_time":0.2667454141},
{"learn":[4.178283162],"iteration":393,"passed_time":0.1729693859,"remaining_time":0.2660392078},
{"learn":[4.176341157],"iteration":394,"passed_time":0.1732502323,"remaining_time":0.2653579508},
{"learn":[4.176041504],"iteration":395,"passed_time":0.1735361206,"remaining_time":0.2646864062},
{"learn":[4.175564513],"iteration":396,"passed_time":0.1737896324,"remaining_time":0.2639676281},
{"learn":[4.170830274],"iteration":397,"passed_time":0.17405877,"remaining_time":0.2632748229},
{"learn":[4.167804808],"iteration":398,"passed_time":0.1743601173,"remaining_time":0.2626326579},
{"learn":[4.165860548],"iteration":399,"passed_time":0.1746310883,"remaining_time":0.2619466324},
{"learn":[4.160950571],"iteration":400,"passed_time":0.1748659325,"remaining_time":0.2612087122},
{"learn":[4.158544115],"iteration":401,"passed_time":0.1751594462,"remaining_time":0.2605605692},
{"learn":[4.154448767],"iteration":402,"passed_time":0.175449043,"remaining_time":0.2599083838},
{"learn":[4.15197457],"iteration":403,"passed_time":0.1757028882,"remaining_time":0.2592052509},
{"learn":[4.149562679],"iteration":404,"passed_time":0.1759278153,"remaining_time":0.2584618521},
{"learn":[4.149327961],"iteration":405,"passed_time":0.1761630346,"remaining_time":0.2577360654},
{"learn":[4.147444889],"iteration":406,"passed_time":0.1764632152,"remaining_time":0.2571073382},
{"learn":[4.147254809],"iteration":407,"passed_time":0.1767197688,"remaining_time":0.2564169195},
{"learn":[4.144589165],"iteration":408,"passed_time":0.1769734057,"remaining_time":0.2557244077},
{"learn":[4.141691034],"iteration":409,"passed_time":0.1772058331,"remaining_time":0.255003516},
{"learn":[4.138893468],"iteration":410,"passed_time":0.1775012636,"remaining_time":0.2543752901},
{"learn":[4.136964597],"iteration":411,"passed_time":0.1778095696,"remaining_time":0.2537670556},
{"learn":[4.133773523],"iteration":412,"passed_time":0.178141585,"remaining_time":0.253193972},
{"learn":[4.131363444],"iteration":413,"passed_time":0.1784731421,"remaining_time":0.2526214041},
{"learn":[4.130228592],"iteration":414,"passed_time":0.1787571554,"remaining_time":0.251982978},
{"learn":[4.12884186],"iteration":415,"passed_time":0.1790717533,"remaining_time":0.2513891922},
{"learn":[4.12413494],"iteration":416,"passed_time":0.179421603,"remaining_time":0.25084603},
{"learn":[4.119422508],"iteration":417,"passed_time":0.179773036,"remaining_time":0.2503059975},
{"learn":[4.117038244],"iteration":418,"passed_time":0.1801077599,"remaining_time":0.2497436957},
{"learn":[4.116067631],"iteration":419,"passed_time":0.1803809393,"remaining_time":0.2490974876},
{"learn":[4.110343455],"iteration":420,"passed_time":0.1806108667,"remaining_time":0.2483935672},
{"learn":[4.105604544],"iteration":421,"passed_time":0.1809018802,"remaining_time":0.247775561},
{"learn":[4.103390131],"iteration":422,"passed_time":0.1812264787,"remaining_time":0.247204913},
{"learn":[4.096724402],"iteration":423,"passed_time":0.1814427804,"remaining_time":0.2464883054},
{"learn":[4.093431279],"iteration":424,"passed_time":0.1817533782,"remaining_time":0.2459016293},
{"learn":[4.091412744],"iteration":425,"passed_time":0.1820128486,"remaining_time":0.2452473594},
{"learn":[4.091192901],"iteration":426,"passed_time":0.1822848613,"remaining_time":0.2446117693},
{"learn":[4.088994581],"iteration":427,"passed_time":0.1825223723,"remaining_time":0.2439317686},
{"learn":[4.087845355],"iteration":428,"passed_time":0.1827847179,"remaining_time":0.2432868855},
{"learn":[4.083650279],"iteration":429,"passed_time":0.1830221039,"remaining_time":0.2426106959},
{"learn":[4.079840652],"iteration":430,"passed_time":0.1833173677,"remaining_time":0.2420129517},
{"learn":[4.075707828],"iteration":431,"passed_time":0.1835755463,"remaining_time":0.241367848},
{"learn":[4.071345409],"iteration":432,"passed_time":0.1838283081,"remaining_time":0.2407174381},
{"learn":[4.067460475],"iteration":433,"passed_time":0.1840604439,"remaining_time":0.2400419614},
{"learn":[4.064914749],"iteration":434,"passed_time":0.1843149558,"remaining_time":0.2393975862},
{"learn":[4.063823175],"iteration":435,"passed_time":0.1845794681,"remaining_time":0.2387679358},
{"learn":[4.058898471],"iteration":436,"passed_time":0.184856481,"remaining_time":0.2381560613},
{"learn":[4.054120355],"iteration":437,"passed_time":0.1851934133,"remaining_time":0.2376225988},
{"learn":[4.052715901],"iteration":438,"passed_time":0.1854751765,"remaining_time":0.2370195307},
{"learn":[4.052114167],"iteration":439,"passed_time":0.1857244797,"remaining_time":0.2363766106},
{"learn":[4.051377267],"iteration":440,"passed_time":0.1859628658,"remaining_time":0.2357216372},
{"learn":[4.049275336],"iteration":441,"passed_time":0.18619621,"remaining_time":0.2350621837},
{"learn":[4.047099198],"iteration":442,"passed_time":0.1864888486,"remaining_time":0.234479207},
{"learn":[4.044348685],"iteration":443,"passed_time":0.1867305266,"remaining_time":0.2338337225},
{"learn":[4.042822379],"iteration":444,"passed_time":0.1869849967,"remaining_time":0.2332060072},
{"learn":[4.041258611],"iteration":445,"passed_time":0.1872669265,"remaining_time":0.2326140747},
{"learn":[4.040044254],"iteration":446,"passed_time":0.1875144797,"remaining_time":0.2319810006},
{"learn":[4.036860137],"iteration":447,"passed_time":0.1878154521,"remaining_time":0.2314154677},
{"learn":[4.036372284],"iteration":448,"passed_time":0.1880994236,"remaining_time":0.2308302504},
{"learn":[4.03368231],"iteration":449,"passed_time":0.1883973542,"remaining_time":0.2302634329},
{"learn":[4.032439519],"iteration":450,"passed_time":0.1886462824,"remaining_time":0.2296381575},
{"learn":[4.032008634],"iteration":451,"passed_time":0.1889289206,"remaining_time":0.229055417},
{"learn":[4.030034932],"iteration":452,"passed_time":0.1891602647,"remaining_time":0.2284120635},
{"learn":[4.028173412],"iteration":453,"passed_time":0.1894265687,"remaining_time":0.2278125695},
{"learn":[4.023806097],"iteration":454,"passed_time":0.1897405,"remaining_time":0.2272715879},
{"learn":[4.020239186],"iteration":455,"passed_time":0.1900063874,"remaining_time":0.2266742867},
{"learn":[4.017384838],"iteration":456,"passed_time":0.1902366481,"remaining_time":0.2260361049},
{"learn":[4.016468229],"iteration":457,"passed_time":0.1905408706,"remaining_time":0.2254872312},
{"learn":[4.014530169],"iteration":458,"passed_time":0.1908611772,"remaining_time":0.224958381},
{"learn":[4.012884822],"iteration":459,"passed_time":0.1912105685,"remaining_time":0.2244645804},
{"learn":[4.008924707],"iteration":460,"passed_time":0.1915172494,"remaining_time":0.2239214695},
{"learn":[4.008286778],"iteration":461,"passed_time":0.191795054,"remaining_time":0.2233457555},
{"learn":[4.006444202],"iteration":462,"passed_time":0.1920321484,"remaining_time":0.2227241116},
{"learn":[4.003284363],"iteration":463,"passed_time":0.1923323707,"remaining_time":0.2221770489},
{"learn":[3.999811484],"iteration":464,"passed_time":0.1926133421,"remaining_time":0.221608899},
{"learn":[3.997483319],"iteration":465,"passed_time":0.1928516449,"remaining_time":0.2209930866},
{"learn":[3.99708333],"iteration":466,"passed_time":0.1931076568,"remaining_time":0.2203991029},
{"learn":[3.995860263],"iteration":467,"passed_time":0.1933516265,"remaining_time":0.2197928745},
{"learn":[3.994131111],"iteration":468,"passed_time":0.1936276393,"remaining_time":0.2192244701},
{"learn":[3.993125499],"iteration":469,"passed_time":0.1938798177,"remaining_time":0.2186304328},
{"learn":[3.992954084],"iteration":470,"passed_time":0.1941867904,"remaining_time":0.2180993887},
{"learn":[3.990635743],"iteration":471,"passed_time":0.1944957631,"remaining_time":0.2175715316},
{"learn":[3.986678254],"iteration":472,"passed_time":0.1947726093,"remaining_time":0.2170088057},
{"learn":[3.986393291],"iteration":473,"passed_time":0.1950229126,"remaining_time":0.2164178313},
{"learn":[3.986152671],"iteration":474,"passed_time":0.1952680074,"remaining_time":0.2158225344},
{"learn":[3.985596662],"iteration":475,"passed_time":0.1954924761,"remaining_time":0.2152060031},
{"learn":[3.983853457],"iteration":476,"passed_time":0.1958399923,"remaining_time":0.2147260293},
{"learn":[3.983263928],"iteration":477,"passed_time":0.1960789201,"remaining_time":0.2141280257},
{"learn":[3.980067202],"iteration":478,"passed_time":0.1963369321,"remaining_time":0.213552279},
{"learn":[3.978115407],"iteration":479,"passed_time":0.1965953608,"remaining_time":0.2129783076},
{"learn":[3.972661644],"iteration":480,"passed_time":0.1968632066,"remaining_time":0.2124158092},
{"learn":[3.969938254],"iteration":481,"passed_time":0.1971506783,"remaining_time":0.2118756253},
{"learn":[3.968211434],"iteration":482,"passed_time":0.1973721886,"remaining_time":0.2112658831},
{"learn":[3.966113368],"iteration":483,"passed_time":0.1976467431,"remaining_time":0.2107142964},
{"learn":[3.962246044],"iteration":484,"passed_time":0.1979103387,"remaining_time":0.2101522153},
{"learn":[3.961319703],"iteration":485,"passed_time":0.1982131028,"remaining_time":0.2096327877},
{"learn":[3.96078191],"iteration":486,"passed_time":0.1984773651,"remaining_time":0.2090736926},
{"learn":[3.958913633],"iteration":487,"passed_time":0.198769587,"remaining_time":0.2085451405},
{"learn":[3.957428286],"iteration":488,"passed_time":0.1990375578,"remaining_time":0.2079922128},
{"learn":[3.952641965],"iteration":489,"passed_time":0.1993033202,"remaining_time":0.2074381496},
{"learn":[3.951486786],"iteration":490,"passed_time":0.1995297058,"remaining_time":0.2068444404},
{"learn":[3.94938344],"iteration":491,"passed_time":0.1997812175,"remaining_time":0.2062781676},
{"learn":[3.947297924],"iteration":492,"passed_time":0.2000500216,"remaining_time":0.2057309553},
{"learn":[3.946284886],"iteration":493,"passed_time":0.2003991212,"remaining_time":0.2052671161},
{"learn":[3.943288204],"iteration":494,"passed_time":0.20065905,"remaining_time":0.2047127682},
{"learn":[3.943076488],"iteration":495,"passed_time":0.2009281459,"remaining_time":0.2041689224},
{"learn":[3.942347078],"iteration":496,"passed_time":0.2012191177,"remaining_time":0.2036483224},
{"learn":[3.940251541],"iteration":497,"passed_time":0.2014720879,"remaining_time":0.2030903376},
{"learn":[3.939011019],"iteration":498,"passed_time":0.2017265997,"remaining_time":0.2025351231},
{"learn":[3.938760512],"iteration":499,"passed_time":0.2019715278,"remaining_time":0.2019715278},
{"learn":[3.934522727],"iteration":500,"passed_time":0.2022639581,"remaining_time":0.2014565171},
{"learn":[3.930091193],"iteration":501,"passed_time":0.2025026775,"remaining_time":0.2008891103},
{"learn":[3.927671752],"iteration":502,"passed_time":0.2027591894,"remaining_time":0.2003405908},
{"learn":[3.927280041],"iteration":503,"passed_time":0.2029821165,"remaining_time":0.1997601781},
{"learn":[3.925987561],"iteration":504,"passed_time":0.2032349199,"remaining_time":0.1992104661},
{"learn":[3.921645957],"iteration":505,"passed_time":0.203509391,"remaining_time":0.1986830814},
{"learn":[3.920333743],"iteration":506,"passed_time":0.2037491522,"remaining_time":0.1981229429},
{"learn":[3.918659461],"iteration":507,"passed_time":0.2039955387,"remaining_time":0.1975704823},
{"learn":[3.916124385],"iteration":508,"passed_time":0.2042336748,"remaining_time":0.1970112658},
{"learn":[3.913849268],"iteration":509,"passed_time":0.2044888533,"remaining_time":0.1964696826},
{"learn":[3.912826119],"iteration":510,"passed_time":0.2048133684,"remaining_time":0.1959955717},
{"learn":[3.910034145],"iteration":511,"passed_time":0.2050512545,"remaining_time":0.1954394769},
{"learn":[3.90792379],"iteration":512,"passed_time":0.2053302258,"remaining_time":0.1949236257},
{"learn":[3.907823851],"iteration":513,"passed_time":0.2062001413,"remaining_time":0.1949674488},
{"learn":[3.904527401],"iteration":514,"passed_time":0.2064371107,"remaining_time":0.1944116479},
{"learn":[3.903378283],"iteration":515,"passed_time":0.2067079149,"remaining_time":0.1938888194},
{"learn":[3.902170135],"iteration":516,"passed_time":0.2069794276,"remaining_time":0.1933676277},
{"learn":[3.899435429],"iteration":517,"passed_time":0.2072331894,"remaining_time":0.1928308828},
{"learn":[3.897497505],"iteration":518,"passed_time":0.2075095773,"remaining_time":0.1923161978},
{"learn":[3.896426119],"iteration":519,"passed_time":0.2077241289,"remaining_time":0.1917453498},
{"learn":[3.896044669],"iteration":520,"passed_time":0.2079808075,"remaining_time":0.1912146004},
{"learn":[3.892795942],"iteration":521,"passed_time":0.2082134017,"remaining_time":0.1906628468},
{"learn":[3.892413888],"iteration":522,"passed_time":0.2084797474,"remaining_time":0.1901430966},
{"learn":[3.891738985],"iteration":523,"passed_time":0.2087443431,"remaining_time":0.1896227239},
{"learn":[3.88822057],"iteration":524,"passed_time":0.2089983966,"remaining_time":0.1890937874},
{"learn":[3.883837053],"iteration":525,"passed_time":0.209236741,"remaining_time":0.18855174},
{"learn":[3.881769742],"iteration":526,"passed_time":0.2095141706,"remaining_time":0.1880459254},
{"learn":[3.880356898],"iteration":527,"passed_time":0.2098119761,"remaining_time":0.1875591908},
{"learn":[3.879250273],"iteration":528,"passed_time":0.2100684047,"remaining_time":0.1870363301},
{"learn":[3.877174493],"iteration":529,"passed_time":0.2103551681,"remaining_time":0.1865413755},
{"learn":[3.875854201],"iteration":530,"passed_time":0.2106403897,"remaining_time":0.1860458432},
{"learn":[3.873189396],"iteration":531,"passed_time":0.210904902,"remaining_time":0.1855328837},
{"learn":[3.871583368],"iteration":532,"passed_time":0.2111758313,"remaining_time":0.1850264788},
{"learn":[3.869622679],"iteration":533,"passed_time":0.2114520525,"remaining_time":0.1845255739},
{"learn":[3.866860164],"iteration":534,"passed_time":0.2117407326,"remaining_time":0.1840363377},
{"learn":[3.864498444],"iteration":535,"passed_time":0.211979827,"remaining_time":0.1835049249},
{"learn":[3.861416322],"iteration":536,"passed_time":0.2122600068,"remaining_time":0.1830100244},
{"learn":[3.860265769],"iteration":537,"passed_time":0.2126092313,"remaining_time":0.1825752135},
{"learn":[3.859328725],"iteration":538,"passed_time":0.2128672017,"remaining_time":0.1820626716},
{"learn":[3.858521278],"iteration":539,"passed_time":0.2131095463,"remaining_time":0.1815377617},
{"learn":[3.85599111],"iteration":540,"passed_time":0.213374392,"remaining_time":0.1810329869},
{"learn":[3.852379816],"iteration":541,"passed_time":0.2136508215,"remaining_time":0.1805388861},
{"learn":[3.851327537],"iteration":542,"passed_time":0.2139503771,"remaining_time":0.1800650504},
{"learn":[3.847854898],"iteration":543,"passed_time":0.2142304318,"remaining_time":0.179575509},
{"learn":[3.847083414],"iteration":544,"passed_time":0.2144902772,"remaining_time":0.1790698645},
{"learn":[3.845397429],"iteration":545,"passed_time":0.214743664,"remaining_time":0.17855975},
{"learn":[3.841933528],"iteration":546,"passed_time":0.2149634659,"remaining_time":0.1780227606},
{"learn":[3.840996474],"iteration":547,"passed_time":0.2152104358,"remaining_time":0.1775093375},
{"learn":[3.838355966],"iteration":548,"passed_time":0.2154964908,"remaining_time":0.1770289933},
{"learn":[3.83342799],"iteration":549,"passed_time":0.2157708785,"remaining_time":0.1765398097},
{"learn":[3.828161535],"iteration":550,"passed_time":0.2160134732,"remaining_time":0.1760254981},
{"learn":[3.823502399],"iteration":551,"passed_time":0.2163261127,"remaining_time":0.175569019},
{"learn":[3.820068862],"iteration":552,"passed_time":0.2166238766,"remaining_time":0.1751010359},
{"learn":[3.817951642],"iteration":553,"passed_time":0.2168788051,"remaining_time":0.1745991825},
{"learn":[3.815785958],"iteration":554,"passed_time":0.2171417757,"remaining_time":0.174104667},
{"learn":[3.81503012],"iteration":555,"passed_time":0.2174340393,"remaining_time":0.1736343767},
{"learn":[3.813529315],"iteration":556,"passed_time":0.2177523458,"remaining_time":0.1731854384},
{"learn":[3.808881326],"iteration":557,"passed_time":0.2179862733,"remaining_time":0.1726701305},
{"learn":[3.808740434],"iteration":558,"passed_time":0.2182435353,"remaining_time":0.1721742381},
{"learn":[3.80714352],"iteration":559,"passed_time":0.2185200482,"remaining_time":0.1716943236},
{"learn":[3.80573346],"iteration":560,"passed_time":0.2187674347,"remaining_time":0.171192342},
{"learn":[3.803370052],"iteration":561,"passed_time":0.2190292386,"remaining_time":0.1707025026},
{"learn":[3.803215211],"iteration":562,"passed_time":0.2192810003,"remaining_time":0.1702056787},
{"learn":[3.801309667],"iteration":563,"passed_time":0.2195337204,"remaining_time":0.1697104647},
{"learn":[3.800003847],"iteration":564,"passed_time":0.2198277341,"remaining_time":0.1692479014},
{"learn":[3.798026138],"iteration":565,"passed_time":0.2201008301,"remaining_time":0.1687698945},
{"learn":[3.794745847],"iteration":566,"passed_time":0.2203649674,"remaining_time":0.1682857688},
{"learn":[3.794312041],"iteration":567,"passed_time":0.2206701066,"remaining_time":0.1678336022},
{"learn":[3.792205926],"iteration":568,"passed_time":0.2209395358,"remaining_time":0.1673549032},
{"learn":[3.788991061],"iteration":569,"passed_time":0.2212053399,"remaining_time":0.1668742038},
{"learn":[3.787391572],"iteration":570,"passed_time":0.2214570599,"remaining_time":0.1663836755},
{"learn":[3.7826445],"iteration":571,"passed_time":0.2217306143,"remaining_time":0.1659103198},
{"learn":[3.781700331],"iteration":572,"passed_time":0.2220265448,"remaining_time":0.1654543362},
{"learn":[3.780045374],"iteration":573,"passed_time":0.2223070995,"remaining_time":0.1649874989},
{"learn":[3.775462644],"iteration":574,"passed_time":0.2225671533,"remaining_time":0.1645061568},
{"learn":[3.773711943],"iteration":575,"passed_time":0.2228137481,"remaining_time":0.1640156757},
{"learn":[3.772415806],"iteration":576,"passed_time":0.2231183873,"remaining_time":0.1635685924},
{"learn":[3.770170875],"iteration":577,"passed_time":0.2233677739,"remaining_time":0.1630816619},
{"learn":[3.765166479],"iteration":578,"passed_time":0.2236313278,"remaining_time":0.1626058532},
{"learn":[3.763976102],"iteration":579,"passed_time":0.223906924,"remaining_time":0.1621394967},
{"learn":[3.760761708],"iteration":580,"passed_time":0.2241286426,"remaining_time":0.1616349419},
{"learn":[3.758155662],"iteration":581,"passed_time":0.2244256981,"remaining_time":0.161185467},
{"learn":[3.756844548],"iteration":582,"passed_time":0.2247307957,"remaining_time":0.1607422672},
{"learn":[3.753098923],"iteration":583,"passed_time":0.2250013083,"remaining_time":0.1602749045},
{"learn":[3.751618946],"iteration":584,"passed_time":0.2252956136,"remaining_time":0.1598250934},
{"learn":[3.751398464],"iteration":585,"passed_time":0.2256343794,"remaining_time":0.1594072237},
{"learn":[3.749920103],"iteration":586,"passed_time":0.2259053087,"remaining_time":0.1589418952},
{"learn":[3.748237465],"iteration":587,"passed_time":0.2261853634,"remaining_time":0.158483622},
{"learn":[3.746021536],"iteration":588,"passed_time":0.2264503757,"remaining_time":0.1580154574},
{"learn":[3.74417648],"iteration":589,"passed_time":0.2267551399,"remaining_time":0.1575756057},
{"learn":[3.738788389],"iteration":590,"passed_time":0.2270020264,"remaining_time":0.157096157},
{"learn":[3.736021611],"iteration":591,"passed_time":0.2272984569,"remaining_time":0.1566516392},
{"learn":[3.734546151],"iteration":592,"passed_time":0.2276057212,"remaining_time":0.1562150565},
{"learn":[3.733527479],"iteration":593,"passed_time":0.2278563578,"remaining_time":0.1557402042},
{"learn":[3.733026392],"iteration":594,"passed_time":0.2280926605,"remaining_time":0.1552563487},
{"learn":[3.730314752],"iteration":595,"passed_time":0.2283647148,"remaining_time":0.1547975584},
{"learn":[3.727342596],"iteration":596,"passed_time":0.2286253103,"remaining_time":0.1543316584},
{"learn":[3.725459604],"iteration":597,"passed_time":0.2289591592,"remaining_time":0.1539156889},
{"learn":[3.723158842],"iteration":598,"passed_time":0.2292742572,"remaining_time":0.153487441},
{"learn":[3.722362756],"iteration":599,"passed_time":0.2295530618,"remaining_time":0.1530353746},
{"learn":[3.721443615],"iteration":600,"passed_time":0.2298359083,"remaining_time":0.1525865681},
{"learn":[3.720743486],"iteration":601,"passed_time":0.2301623819,"remaining_time":0.1521671561},
{"learn":[3.720215334],"iteration":602,"passed_time":0.2304126435,"remaining_time":0.1516978764},
{"learn":[3.719436563],"iteration":603,"passed_time":0.2306798226,"remaining_time":0.1512404135},
{"learn":[3.715046574],"iteration":604,"passed_time":0.2309207922,"remaining_time":0.1507664676},
{"learn":[3.71443396],"iteration":605,"passed_time":0.2311682204,"remaining_time":0.1502974898},
{"learn":[3.712938941],"iteration":606,"passed_time":0.2314100649,"remaining_time":0.1498256269},
{"learn":[3.712814764],"iteration":607,"passed_time":0.2316932031,"remaining_time":0.1493811441},
{"learn":[3.71235348],"iteration":608,"passed_time":0.2319351311,"remaining_time":0.1489107327},
{"learn":[3.711223749],"iteration":609,"passed_time":0.23216285,"remaining_time":0.1484319861},
{"learn":[3.710755648],"iteration":610,"passed_time":0.2324252789,"remaining_time":0.1479761595},
{"learn":[3.708668039],"iteration":611,"passed_time":0.2326572063,"remaining_time":0.1475016275},
{"learn":[3.705623591],"iteration":612,"passed_time":0.2329683458,"remaining_time":0.1470778953},
{"learn":[3.704045802],"iteration":613,"passed_time":0.2332251911,"remaining_time":0.146620397},
{"learn":[3.699915209],"iteration":614,"passed_time":0.2334801197,"remaining_time":0.1461623513},
{"learn":[3.696182221],"iteration":615,"passed_time":0.2337472571,"remaining_time":0.1457125758},
{"learn":[3.694263278],"iteration":616,"passed_time":0.2340239783,"remaining_time":0.1452693415},
{"learn":[3.693810229],"iteration":617,"passed_time":0.2342956993,"remaining_time":0.1448235552},
{"learn":[3.690900932],"iteration":618,"passed_time":0.2345770041,"remaining_time":0.1443842303},
{"learn":[3.688020895],"iteration":619,"passed_time":0.2348236822,"remaining_time":0.1439241923},
{"learn":[3.685491894],"iteration":620,"passed_time":0.2351081954,"remaining_time":0.1434879325},
{"learn":[3.684328128],"iteration":621,"passed_time":0.2353935004,"remaining_time":0.1430526417},
{"learn":[3.680640153],"iteration":622,"passed_time":0.2356788053,"remaining_time":0.1426178324},
{"learn":[3.678932783],"iteration":623,"passed_time":0.2359324422,"remaining_time":0.1421644203},
{"learn":[3.674167041],"iteration":624,"passed_time":0.2361564109,"remaining_time":0.1416938465},
{"learn":[3.672200976],"iteration":625,"passed_time":0.236429382,"remaining_time":0.1412533368},
{"learn":[3.670606604],"iteration":626,"passed_time":0.2366655179,"remaining_time":0.1407914485},
{"learn":[3.665506042],"iteration":627,"passed_time":0.2369242383,"remaining_time":0.1403436571},
{"learn":[3.664214007],"iteration":628,"passed_time":0.237202918,"remaining_time":0.1399082394},
{"learn":[3.66261643],"iteration":629,"passed_time":0.2374519712,"remaining_time":0.1394559196},
{"learn":[3.662118449],"iteration":630,"passed_time":0.2377196087,"remaining_time":0.1390151119},
{"learn":[3.660871366],"iteration":631,"passed_time":0.2379591198,"remaining_time":0.1385584748},
{"learn":[3.656695243],"iteration":632,"passed_time":0.2382040896,"remaining_time":0.1381056886},
{"learn":[3.654497801],"iteration":633,"passed_time":0.2384420173,"remaining_time":0.1376494926},
{"learn":[3.654189134],"iteration":634,"passed_time":0.2387307391,"remaining_time":0.1372231807},
{"learn":[3.653957699],"iteration":635,"passed_time":0.2389774589,"remaining_time":0.1367732626},
{"learn":[3.651920725],"iteration":636,"passed_time":0.2393126829,"remaining_time":0.1363744174},
{"learn":[3.65106705],"iteration":637,"passed_time":0.2395832788,"remaining_time":0.1359391018},
{"learn":[3.650612844],"iteration":638,"passed_time":0.2398529997,"remaining_time":0.1355038073},
{"learn":[3.649884732],"iteration":639,"passed_time":0.2401215955,"remaining_time":0.1350683975},
{"learn":[3.646276182],"iteration":640,"passed_time":0.2403706904,"remaining_time":0.1346225864},
{"learn":[3.645808194],"iteration":641,"passed_time":0.2406728295,"remaining_time":0.1342069672},
{"learn":[3.645042989],"iteration":642,"passed_time":0.2409015068,"remaining_time":0.1337509144},
{"learn":[3.639864499],"iteration":643,"passed_time":0.2411943538,"remaining_time":0.1333310403},
{"learn":[3.637318478],"iteration":644,"passed_time":0.2414538242,"remaining_time":0.1328931901},
{"learn":[3.636344905],"iteration":645,"passed_time":0.2417131279,"remaining_time":0.1324558008},
{"learn":[3.634754643],"iteration":646,"passed_time":0.242015767,"remaining_time":0.1320426055},
{"learn":[3.630724975],"iteration":647,"passed_time":0.2422654037,"remaining_time":0.13160096},
{"learn":[3.629408252],"iteration":648,"passed_time":0.2425466667,"remaining_time":0.1311770108},
{"learn":[3.62790646],"iteration":649,"passed_time":0.2428043454,"remaining_time":0.1307408014},
{"learn":[3.627388973],"iteration":650,"passed_time":0.2430878169,"remaining_time":0.1303189679},
{"learn":[3.625163557],"iteration":651,"passed_time":0.2433506208,"remaining_time":0.1298865277},
{"learn":[3.623701985],"iteration":652,"passed_time":0.2435994658,"remaining_time":0.1294471893},
{"learn":[3.622342639],"iteration":653,"passed_time":0.2438956462,"remaining_time":0.1290334764},
{"learn":[3.621130639],"iteration":654,"passed_time":0.2441301155,"remaining_time":0.1285876181},
{"learn":[3.619125665],"iteration":655,"passed_time":0.2444522555,"remaining_time":0.1281883779},
{"learn":[3.618878783],"iteration":656,"passed_time":0.2446923916,"remaining_time":0.1277465606},
{"learn":[3.616207429],"iteration":657,"passed_time":0.2449648627,"remaining_time":0.1273221627},
{"learn":[3.61206486],"iteration":658,"passed_time":0.245257668,"remaining_time":0.1269087478},
{"learn":[3.611955873],"iteration":659,"passed_time":0.2455101797,"remaining_time":0.1264749411},
{"learn":[3.610713743],"iteration":660,"passed_time":0.2457647749,"remaining_time":0.1260427514},
{"learn":[3.610044025],"iteration":661,"passed_time":0.246025037,"remaining_time":0.1256139917},
{"learn":[3.607342669],"iteration":662,"passed_time":0.2463000081,"remaining_time":0.1251932168},
{"learn":[3.602510618],"iteration":663,"passed_time":0.2465412694,"remaining_time":0.1247558231},
{"learn":[3.600492392],"iteration":664,"passed_time":0.2468444085,"remaining_time":0.1243501907},
{"learn":[3.597171065],"iteration":665,"passed_time":0.247084628,"remaining_time":0.1239133119},
{"learn":[3.594358798],"iteration":666,"passed_time":0.2473591825,"remaining_time":0.1234941646},
{"learn":[3.593945251],"iteration":667,"passed_time":0.2476281533,"remaining_time":0.123072675},
{"learn":[3.593607748],"iteration":668,"passed_time":0.2479528768,"remaining_time":0.122679226},
{"learn":[3.592238714],"iteration":669,"passed_time":0.2482103054,"remaining_time":0.122252837},
{"learn":[3.590144654],"iteration":670,"passed_time":0.248438316,"remaining_time":0.1218125275},
{"learn":[3.587151536],"iteration":671,"passed_time":0.2486959114,"remaining_time":0.1213872901},
{"learn":[3.586070865],"iteration":672,"passed_time":0.2489422562,"remaining_time":0.1209570843},
{"learn":[3.585102746],"iteration":673,"passed_time":0.2491879759,"remaining_time":0.1205271219},
{"learn":[3.584362847],"iteration":674,"passed_time":0.2494315289,"remaining_time":0.1200966621},
{"learn":[3.581407561],"iteration":675,"passed_time":0.2497279177,"remaining_time":0.1196920789},
{"learn":[3.57919422],"iteration":676,"passed_time":0.2499540949,"remaining_time":0.1192543171},
{"learn":[3.577632204],"iteration":677,"passed_time":0.2502051066,"remaining_time":0.1188289739},
{"learn":[3.573911195],"iteration":678,"passed_time":0.250463827,"remaining_time":0.1184077886},
{"learn":[3.573408216],"iteration":679,"passed_time":0.2507246308,"remaining_time":0.1179880616},
{"learn":[3.571076482],"iteration":680,"passed_time":0.2509896431,"remaining_time":0.1175707726},
{"learn":[3.568177107],"iteration":681,"passed_time":0.2512879904,"remaining_time":0.1171694735},
{"learn":[3.564824621],"iteration":682,"passed_time":0.2515216262,"remaining_time":0.1167384415},
{"learn":[3.562475026],"iteration":683,"passed_time":0.2518012643,"remaining_time":0.116329239},
{"learn":[3.561226889],"iteration":684,"passed_time":0.2520947779,"remaining_time":0.1159267957},
{"learn":[3.559383467],"iteration":685,"passed_time":0.2523437062,"remaining_time":0.115504262},
{"learn":[3.555209766],"iteration":686,"passed_time":0.2526212191,"remaining_time":0.115095257},
{"learn":[3.55345383],"iteration":687,"passed_time":0.2528959819,"remaining_time":0.1146853871},
{"learn":[3.552300968],"iteration":688,"passed_time":0.2531367014,"remaining_time":0.114260543},
{"learn":[3.551253986],"iteration":689,"passed_time":0.2534040472,"remaining_time":0.1138481951},
{"learn":[3.549807725],"iteration":690,"passed_time":0.2536878938,"remaining_time":0.1134436457},
{"learn":[3.547992926],"iteration":691,"passed_time":0.2539732404,"remaining_time":0.1130401128},
{"learn":[3.545438607],"iteration":692,"passed_time":0.2542545035,"remaining_time":0.1126351119},
{"learn":[3.543313763],"iteration":693,"passed_time":0.2545355582,"remaining_time":0.1122303758},
{"learn":[3.542962896],"iteration":694,"passed_time":0.2548046957,"remaining_time":0.1118207658},
{"learn":[3.539800465],"iteration":695,"passed_time":0.2550432485,"remaining_time":0.1113982005},
{"learn":[3.53953187],"iteration":696,"passed_time":0.2553549714,"remaining_time":0.1110079718},
{"learn":[3.536332425],"iteration":697,"passed_time":0.2555943575,"remaining_time":0.1105866704},
{"learn":[3.534993327],"iteration":698,"passed_time":0.2558901629,"remaining_time":0.1101901846},
{"learn":[3.531637011],"iteration":699,"passed_time":0.256164009,"remaining_time":0.1097845753},
{"learn":[3.531040284],"iteration":700,"passed_time":0.2564561893,"remaining_time":0.1093871621},
{"learn":[3.529973872],"iteration":701,"passed_time":0.2567484529,"remaining_time":0.108990084},
{"learn":[3.527325183],"iteration":702,"passed_time":0.2570097151,"remaining_time":0.1085802068},
{"learn":[3.527200815],"iteration":703,"passed_time":0.2573290633,"remaining_time":0.1081951743},
{"learn":[3.523459911],"iteration":704,"passed_time":0.2576125765,"remaining_time":0.1077953334},
{"learn":[3.522729934],"iteration":705,"passed_time":0.2579192574,"remaining_time":0.1074054698},
{"learn":[3.522260582],"iteration":706,"passed_time":0.2582109793,"remaining_time":0.1070096421},
{"learn":[3.518641591],"iteration":707,"passed_time":0.2584555324,"remaining_time":0.1065946546},
{"learn":[3.516856405],"iteration":708,"passed_time":0.2587361288,"remaining_time":0.1061949414},
{"learn":[3.515083413],"iteration":709,"passed_time":0.2590057663,"remaining_time":0.1057910877},
{"learn":[3.514671214],"iteration":710,"passed_time":0.2592817792,"remaining_time":0.1053902028},
{"learn":[3.512617621],"iteration":711,"passed_time":0.2595642923,"remaining_time":0.104992298},
{"learn":[3.510747971],"iteration":712,"passed_time":0.2598250961,"remaining_time":0.1045859784},
{"learn":[3.508149266],"iteration":713,"passed_time":0.260101359,"remaining_time":0.1041862586},
{"learn":[3.504557165],"iteration":714,"passed_time":0.2603498289,"remaining_time":0.1037758059},
{"learn":[3.501367208],"iteration":715,"passed_time":0.2606683021,"remaining_time":0.1033935723},
{"learn":[3.497593362],"iteration":716,"passed_time":0.2609444816,"remaining_time":0.1029948233},
{"learn":[3.496291169],"iteration":717,"passed_time":0.2612058271,"remaining_time":0.1025905895},
{"learn":[3.49330374],"iteration":718,"passed_time":0.2622665848,"remaining_time":0.1024991799},
{"learn":[3.490044385],"iteration":719,"passed_time":0.2625386808,"remaining_time":0.1020983759},
{"learn":[3.488891789],"iteration":720,"passed_time":0.2628075683,"remaining_time":0.1016966873},
{"learn":[3.486869081],"iteration":721,"passed_time":0.2630540798,"remaining_time":0.1012867509},
{"learn":[3.486303638],"iteration":722,"passed_time":0.2633186755,"remaining_time":0.1008841952},
{"learn":[3.486035862],"iteration":723,"passed_time":0.2636083973,"remaining_time":0.100491599},
{"learn":[3.482668951],"iteration":724,"passed_time":0.2638774931,"remaining_time":0.1000914629},
{"learn":[3.47820549],"iteration":725,"passed_time":0.2641354635,"remaining_time":0.09968748897},
{"learn":[3.474392283],"iteration":726,"passed_time":0.2643984757,"remaining_time":0.09928581},
{"learn":[3.472268163],"iteration":727,"passed_time":0.2646825306,"remaining_time":0.09889237407},
{"learn":[3.471209164],"iteration":728,"passed_time":0.2649981286,"remaining_time":0.09851096414},
{"learn":[3.470049971],"iteration":729,"passed_time":0.2652588074,"remaining_time":0.09810942193},
{"learn":[3.469078654],"iteration":730,"passed_time":0.2655091941,"remaining_time":0.09770447772},
{"learn":[3.468643292],"iteration":731,"passed_time":0.2657915822,"remaining_time":0.09731167219},
{"learn":[3.468134848],"iteration":732,"passed_time":0.2660405938,"remaining_time":0.09690701031},
{"learn":[3.467820182],"iteration":733,"passed_time":0.2663336075,"remaining_time":0.09651871879},
{"learn":[3.465776156],"iteration":734,"passed_time":0.2666003282,"remaining_time":0.09612120678},
{"learn":[3.463037608],"iteration":735,"passed_time":0.2668585486,"remaining_time":0.09572100112},
{"learn":[3.45965637],"iteration":736,"passed_time":0.2670896427,"remaining_time":0.09531150071},
{"learn":[3.457275091],"iteration":737,"passed_time":0.2673125281,"remaining_time":0.09489956958},
{"learn":[3.455522955],"iteration":738,"passed_time":0.2675704567,"remaining_time":0.09450052666},
{"learn":[3.451270508],"iteration":739,"passed_time":0.2678788461,"remaining_time":0.09411959457},
{"learn":[3.450978947],"iteration":740,"passed_time":0.2681277743,"remaining_time":0.09371807497},
{"learn":[3.450608492],"iteration":741,"passed_time":0.268400537,"remaining_time":0.09332525412},
{"learn":[3.448122004],"iteration":742,"passed_time":0.2686398398,"remaining_time":0.09292118283},
{"learn":[3.445646714],"iteration":743,"passed_time":0.2688865597,"remaining_time":0.09252010655},
{"learn":[3.44411263],"iteration":744,"passed_time":0.2691122368,"remaining_time":0.09211224214},
{"learn":[3.443264164],"iteration":745,"passed_time":0.2693504979,"remaining_time":0.09170915077},
{"learn":[3.439521363],"iteration":746,"passed_time":0.269581592,"remaining_time":0.09130407333},
{"learn":[3.436809225],"iteration":747,"passed_time":0.2698126028,"remaining_time":0.09089943302},
{"learn":[3.435509465],"iteration":748,"passed_time":0.2701056998,"remaining_time":0.09051606227},
{"learn":[3.434450277],"iteration":749,"passed_time":0.2704132141,"remaining_time":0.09013773802},
{"learn":[3.431786753],"iteration":750,"passed_time":0.270689977,"remaining_time":0.08974940647},
{"learn":[3.430150302],"iteration":751,"passed_time":0.2709159875,"remaining_time":0.08934463417},
{"learn":[3.42696281],"iteration":752,"passed_time":0.271170541,"remaining_time":0.08894969937},
{"learn":[3.426870334],"iteration":753,"passed_time":0.2714248862,"remaining_time":0.08855506896},
{"learn":[3.425200309],"iteration":754,"passed_time":0.2716823148,"remaining_time":0.08816181077},
{"learn":[3.423383783],"iteration":755,"passed_time":0.2719265345,"remaining_time":0.08776464871},
{"learn":[3.422752979],"iteration":756,"passed_time":0.2721694208,"remaining_time":0.0873674627},
{"learn":[3.420845924],"iteration":757,"passed_time":0.2725234373,"remaining_time":0.08700616336},
{"learn":[3.418917862],"iteration":758,"passed_time":0.272817201,"remaining_time":0.08662575157},
{"learn":[3.417095735],"iteration":759,"passed_time":0.2730760047,"remaining_time":0.0862345278},
{"learn":[3.414391848],"iteration":760,"passed_time":0.2733321416,"remaining_time":0.08584281452},
{"learn":[3.41426711],"iteration":761,"passed_time":0.2735820283,"remaining_time":0.08544950489},
{"learn":[3.411976013],"iteration":762,"passed_time":0.2738224561,"remaining_time":0.08505363316},
{"learn":[3.408614844],"iteration":763,"passed_time":0.2740607589,"remaining_time":0.08465751191},
{"learn":[3.407906721],"iteration":764,"passed_time":0.2743116872,"remaining_time":0.0842656817},
{"learn":[3.407494015],"iteration":765,"passed_time":0.2745734911,"remaining_time":0.08387754166},
{"learn":[3.406287128],"iteration":766,"passed_time":0.2748764219,"remaining_time":0.08350222463},
{"learn":[3.404600442],"iteration":767,"passed_time":0.2751274752,"remaining_time":0.0831114248},
{"learn":[3.404012662],"iteration":768,"passed_time":0.2753590277,"remaining_time":0.08271513054},
{"learn":[3.400398762],"iteration":769,"passed_time":0.2756062475,"remaining_time":0.08232394406},
{"learn":[3.399737714],"iteration":770,"passed_time":0.275890094,"remaining_time":0.08194400977},
{"learn":[3.399185251],"iteration":771,"passed_time":0.276140689,"remaining_time":0.08155450402},
{"learn":[3.397245411],"iteration":772,"passed_time":0.2764281191,"remaining_time":0.08117617469},
{"learn":[3.396229831],"iteration":773,"passed_time":0.2766710887,"remaining_time":0.08078509826},
{"learn":[3.394002836],"iteration":774,"passed_time":0.2769477683,"remaining_time":0.08040419079},
{"learn":[3.389617243],"iteration":775,"passed_time":0.277171487,"remaining_time":0.0800082643},
{"learn":[3.385426488],"iteration":776,"passed_time":0.277384497,"remaining_time":0.07960970762},
{"learn":[3.385072258],"iteration":777,"passed_time":0.2776390921,"remaining_time":0.07922349416},
{"learn":[3.383842366],"iteration":778,"passed_time":0.277893854,"remaining_time":0.0788376659},
{"learn":[3.380110746],"iteration":779,"passed_time":0.2781437406,"remaining_time":0.07845079864},
{"learn":[3.378595218],"iteration":780,"passed_time":0.2783839185,"remaining_time":0.07806155973},
{"learn":[3.377371219],"iteration":781,"passed_time":0.2786148876,"remaining_time":0.0776701349},
{"learn":[3.375814782],"iteration":782,"passed_time":0.2788967757,"remaining_time":0.07729323158},
{"learn":[3.374195887],"iteration":783,"passed_time":0.2791599129,"remaining_time":0.07691140459},
{"learn":[3.373704309],"iteration":784,"passed_time":0.2794142998,"remaining_time":0.07652748338},
{"learn":[3.372971757],"iteration":785,"passed_time":0.2797116053,"remaining_time":0.07615557701},
{"learn":[3.371565136],"iteration":786,"passed_time":0.2799795761,"remaining_time":0.07577592085},
{"learn":[3.3700309],"iteration":787,"passed_time":0.2802714647,"remaining_time":0.07540298289},
{"learn":[3.368186663],"iteration":788,"passed_time":0.2805417273,"remaining_time":0.07502446699},
{"learn":[3.366710398],"iteration":789,"passed_time":0.2808354909,"remaining_time":0.07465247228},
{"learn":[3.364598042],"iteration":790,"passed_time":0.2811559642,"remaining_time":0.07428773264},
{"learn":[3.36348442],"iteration":791,"passed_time":0.2813925585,"remaining_time":0.07390107598},
{"learn":[3.362001759],"iteration":792,"passed_time":0.2816442369,"remaining_time":0.07351873524},
{"learn":[3.361580401],"iteration":793,"passed_time":0.2818819563,"remaining_time":0.07313310202},
{"learn":[3.359543675],"iteration":794,"passed_time":0.2821580942,"remaining_time":0.07275774756},
{"learn":[3.35766119],"iteration":795,"passed_time":0.2824163562,"remaining_time":0.07237806114},
{"learn":[3.354592969],"iteration":796,"passed_time":0.2827099532,"remaining_time":0.07200767942},
{"learn":[3.350985986],"iteration":797,"passed_time":0.2829858411,"remaining_time":0.07163300738},
{"learn":[3.349589624],"iteration":798,"passed_time":0.2832276023,"remaining_time":0.07124999758},
{"learn":[3.349110856],"iteration":799,"passed_time":0.2834706553,"remaining_time":0.07086766382},
{"learn":[3.345315441],"iteration":800,"passed_time":0.2837562936,"remaining_time":0.07049625771},
{"learn":[3.34397474],"iteration":801,"passed_time":0.2840028467,"remaining_time":0.07011541603},
{"learn":[3.343800902],"iteration":802,"passed_time":0.2842378993,"remaining_time":0.06973208739},
{"learn":[3.342329465],"iteration":803,"passed_time":0.2845216209,"remaining_time":0.06936099216},
{"learn":[3.34220347],"iteration":804,"passed_time":0.2847989671,"remaining_time":0.06898856968},
{"learn":[3.341279219],"iteration":805,"passed_time":0.2850847721,"remaining_time":0.06861841909},
{"learn":[3.337329521],"iteration":806,"passed_time":0.2853266584,"remaining_time":0.06823797406},
{"learn":[3.336708453],"iteration":807,"passed_time":0.2855812535,"remaining_time":0.06786089193},
{"learn":[3.333252703],"iteration":808,"passed_time":0.2858975183,"remaining_time":0.06749867242},
{"learn":[3.332186769],"iteration":809,"passed_time":0.286156947,"remaining_time":0.06712323449},
{"learn":[3.330594851],"iteration":810,"passed_time":0.2863757905,"remaining_time":0.06673862443},
{"learn":[3.327867442],"iteration":811,"passed_time":0.2866960138,"remaining_time":0.06637789482},
{"learn":[3.327563111],"iteration":812,"passed_time":0.2869423586,"remaining_time":0.0660002719},
{"learn":[3.326308994],"iteration":813,"passed_time":0.2872286636,"remaining_time":0.06563210249},
{"learn":[3.326249879],"iteration":814,"passed_time":0.2874688414,"remaining_time":0.06525366339},
{"learn":[3.322336238],"iteration":815,"passed_time":0.2877967734,"remaining_time":0.06489535086},
{"learn":[3.320491154],"iteration":816,"passed_time":0.2880713278,"remaining_time":0.06452515666},
{"learn":[3.320434271],"iteration":817,"passed_time":0.2883670916,"remaining_time":0.06415991524},
{"learn":[3.319609638],"iteration":818,"passed_time":0.2886297288,"remaining_time":0.06378752248},
{"learn":[3.316182682],"iteration":819,"passed_time":0.2889026165,"remaining_time":0.06341764753},
{"learn":[3.313126612],"iteration":820,"passed_time":0.2891696289,"remaining_time":0.06304672787},
{"learn":[3.311222803],"iteration":821,"passed_time":0.2894298077,"remaining_time":0.06267458123},
{"learn":[3.309627335],"iteration":822,"passed_time":0.2896748191,"remaining_time":0.0622994447},
{"learn":[3.307974895],"iteration":823,"passed_time":0.2899237057,"remaining_time":0.06192545171},
{"learn":[3.307321505],"iteration":824,"passed_time":0.2902130525,"remaining_time":0.06156034447},
{"learn":[3.306759087],"iteration":825,"passed_time":0.2904868153,"remaining_time":0.06119213784},
{"learn":[3.30484037],"iteration":826,"passed_time":0.2907051588,"remaining_time":0.06081256646},
{"learn":[3.30201994],"iteration":827,"passed_time":0.2909726712,"remaining_time":0.06044359837},
{"learn":[3.299302297],"iteration":828,"passed_time":0.2912456423,"remaining_time":0.060076001},
{"learn":[3.298132671],"iteration":829,"passed_time":0.2915148631,"remaining_time":0.05970786353},
{"learn":[3.296976183],"iteration":830,"passed_time":0.2918796301,"remaining_time":0.05935939529},
{"learn":[3.293144745],"iteration":831,"passed_time":0.2921232664,"remaining_time":0.0589864288},
{"learn":[3.290284404],"iteration":832,"passed_time":0.2923691112,"remaining_time":0.05861421558},
{"learn":[3.288285745],"iteration":833,"passed_time":0.2925820795,"remaining_time":0.05823576162},
{"learn":[3.286662667],"iteration":834,"passed_time":0.2928756348,"remaining_time":0.05787362843},
{"learn":[3.285692682],"iteration":835,"passed_time":0.293145064,"remaining_time":0.05750692643},
{"learn":[3.284565611],"iteration":836,"passed_time":0.2933829501,"remaining_time":0.05713431406},
{"learn":[3.283897383],"iteration":837,"passed_time":0.2936292949,"remaining_time":0.05676365844},
{"learn":[3.280712855],"iteration":838,"passed_time":0.2938806816,"remaining_time":0.05639426667},
{"learn":[3.280468341],"iteration":839,"passed_time":0.2941570695,"remaining_time":0.05602991799},
{"learn":[3.277814895],"iteration":840,"passed_time":0.2944576668,"remaining_time":0.05567035555},
{"learn":[3.276316385],"iteration":841,"passed_time":0.2946791354,"remaining_time":0.0552960848},
{"learn":[3.27557063],"iteration":842,"passed_time":0.2949901499,"remaining_time":0.05493885354},
{"learn":[3.27499628],"iteration":843,"passed_time":0.2953113732,"remaining_time":0.05458361874},
{"learn":[3.273569958],"iteration":844,"passed_time":0.2956388884,"remaining_time":0.05422961859},
{"learn":[3.269665595],"iteration":845,"passed_time":0.2959159013,"remaining_time":0.05386648795},
{"learn":[3.267984685],"iteration":846,"passed_time":0.2961499122,"remaining_time":0.05349579288},
{"learn":[3.267702508],"iteration":847,"passed_time":0.2964002989,"remaining_time":0.05312835546},
{"learn":[3.266671924],"iteration":848,"passed_time":0.2966493938,"remaining_time":0.05276096404},
{"learn":[3.265359825],"iteration":849,"passed_time":0.2969300736,"remaining_time":0.05239942475},
{"learn":[3.2618983],"iteration":850,"passed_time":0.2972303375,"remaining_time":0.05204150446},
{"learn":[3.260456253],"iteration":851,"passed_time":0.297518476,"remaining_time":0.05168161319},
{"learn":[3.258389147],"iteration":852,"passed_time":0.2977969056,"remaining_time":0.05132021702},
{"learn":[3.258108469],"iteration":853,"passed_time":0.2980634597,"remaining_time":0.05095698491},
{"learn":[3.256424936],"iteration":854,"passed_time":0.2983616402,"remaining_time":0.05059934249},
{"learn":[3.254817983],"iteration":855,"passed_time":0.2986064016,"remaining_time":0.05023285261},
{"learn":[3.253898449],"iteration":856,"passed_time":0.298915666,"remaining_time":0.04987740985},
{"learn":[3.253023652],"iteration":857,"passed_time":0.2991767198,"remaining_time":0.04951409582},
{"learn":[3.252845542],"iteration":858,"passed_time":0.2994406488,"remaining_time":0.04915149182},
{"learn":[3.252316026],"iteration":859,"passed_time":0.2997416211,"remaining_time":0.04879514762},
{"learn":[3.24975301],"iteration":860,"passed_time":0.3000166339,"remaining_time":0.04843474113},
{"learn":[3.249151075],"iteration":861,"passed_time":0.3002203517,"remaining_time":0.04806311896},
{"learn":[3.246257135],"iteration":862,"passed_time":0.3005053233,"remaining_time":0.04770478482},
{"learn":[3.243826471],"iteration":863,"passed_time":0.3007846697,"remaining_time":0.04734573504},
{"learn":[3.243190653],"iteration":864,"passed_time":0.3010548906,"remaining_time":0.04698544535},
{"learn":[3.24008797],"iteration":865,"passed_time":0.301313986,"remaining_time":0.04662364217},
{"learn":[3.240036811],"iteration":866,"passed_time":0.3015789567,"remaining_time":0.0462629772},
{"learn":[3.238676314],"iteration":867,"passed_time":0.3018988882,"remaining_time":0.04591089083},
{"learn":[3.237848782],"iteration":868,"passed_time":0.3021685674,"remaining_time":0.04555130303},
{"learn":[3.236405498],"iteration":869,"passed_time":0.3024187458,"remaining_time":0.04518900799},
{"learn":[3.233378068],"iteration":870,"passed_time":0.3026888833,"remaining_time":0.04482992646},
{"learn":[3.233169169],"iteration":871,"passed_time":0.3029538123,"remaining_time":0.04447028438},
{"learn":[3.232434885],"iteration":872,"passed_time":0.3031764894,"remaining_time":0.04410471266},
{"learn":[3.229978115],"iteration":873,"passed_time":0.3035095882,"remaining_time":0.04375538686},
{"learn":[3.229648848],"iteration":874,"passed_time":0.3037856427,"remaining_time":0.04339794896},
{"learn":[3.227208761],"iteration":875,"passed_time":0.3040498217,"remaining_time":0.04303901586},
{"learn":[3.226258869],"iteration":876,"passed_time":0.3042967498,"remaining_time":0.0426778794},
{"learn":[3.225331995],"iteration":877,"passed_time":0.3045571786,"remaining_time":0.04231887904},
{"learn":[3.221968268],"iteration":878,"passed_time":0.3048747768,"remaining_time":0.04196797268},
{"learn":[3.221166317],"iteration":879,"passed_time":0.3051430392,"remaining_time":0.04161041444},
{"learn":[3.220047503],"iteration":880,"passed_time":0.3054296776,"remaining_time":0.04125554101},
{"learn":[3.21982781],"iteration":881,"passed_time":0.305702857,"remaining_time":0.04089902168},
{"learn":[3.216693405],"iteration":882,"passed_time":0.3059730362,"remaining_time":0.04054229359},
{"learn":[3.214798761],"iteration":883,"passed_time":0.306276592,"remaining_time":0.04019014103},
{"learn":[3.214395085],"iteration":884,"passed_time":0.3065316039,"remaining_time":0.03983179034},
{"learn":[3.213470696],"iteration":885,"passed_time":0.3067752819,"remaining_time":0.0394722146},
{"learn":[3.211595017],"iteration":886,"passed_time":0.3070613786,"remaining_time":0.03911830415},
{"learn":[3.210965255],"iteration":887,"passed_time":0.3073865187,"remaining_time":0.03876947083},
{"learn":[3.209413583],"iteration":888,"passed_time":0.3076700319,"remaining_time":0.0384154933},
{"learn":[3.208331683],"iteration":889,"passed_time":0.3079696292,"remaining_time":0.03806366203},
{"learn":[3.207110711],"iteration":890,"passed_time":0.3082162657,"remaining_time":0.03770546909},
{"learn":[3.204519413],"iteration":891,"passed_time":0.3084772778,"remaining_time":0.03734926682},
{"learn":[3.201421296],"iteration":892,"passed_time":0.3087499155,"remaining_time":0.03699467073},
{"learn":[3.200691259],"iteration":893,"passed_time":0.3090908064,"remaining_time":0.03664835064},
{"learn":[3.200485067],"iteration":894,"passed_time":0.3093531519,"remaining_time":0.03629282788},
{"learn":[3.197467568],"iteration":895,"passed_time":0.309604497,"remaining_time":0.03593623625},
{"learn":[3.195838544],"iteration":896,"passed_time":0.3098452582,"remaining_time":0.03557866398},
{"learn":[3.195671746],"iteration":897,"passed_time":0.3101004784,"remaining_time":0.0352229942},
{"learn":[3.194213094],"iteration":898,"passed_time":0.3103482399,"remaining_time":0.03486670993},
{"learn":[3.192884691],"iteration":899,"passed_time":0.3106537541,"remaining_time":0.03451708379},
{"learn":[3.188364239],"iteration":900,"passed_time":0.310930017,"remaining_time":0.03416434149},
{"learn":[3.185219478],"iteration":901,"passed_time":0.3112077383,"remaining_time":0.03381192722},
{"learn":[3.184120387],"iteration":902,"passed_time":0.3114934599,"remaining_time":0.03346053777},
{"learn":[3.183725321],"iteration":903,"passed_time":0.3117618474,"remaining_time":0.03310745282},
{"learn":[3.181264554],"iteration":904,"passed_time":0.3120199844,"remaining_time":0.03275347903},
{"learn":[3.180741589],"iteration":905,"passed_time":0.312398877,"remaining_time":0.03241224552},
{"learn":[3.179782639],"iteration":906,"passed_time":0.3126571391,"remaining_time":0.03205856001},
{"learn":[3.176377564],"iteration":907,"passed_time":0.3130349483,"remaining_time":0.03171719741},
{"learn":[3.174078182],"iteration":908,"passed_time":0.3132905436,"remaining_time":0.03136351976},
{"learn":[3.171242379],"iteration":909,"passed_time":0.3135483472,"remaining_time":0.0310102761},
{"learn":[3.170421012],"iteration":910,"passed_time":0.3138551532,"remaining_time":0.03066202923},
{"learn":[3.170087224],"iteration":911,"passed_time":0.3141230406,"remaining_time":0.03031011796},
{"learn":[3.167303059],"iteration":912,"passed_time":0.3144266798,"remaining_time":0.02996179753},
{"learn":[3.16705966],"iteration":913,"passed_time":0.3146688577,"remaining_time":0.02960779186},
{"learn":[3.165667683],"iteration":914,"passed_time":0.3149329533,"remaining_time":0.0292560667},
{"learn":[3.164689733],"iteration":915,"passed_time":0.3152297172,"remaining_time":0.02890752865},
{"learn":[3.163311455],"iteration":916,"passed_time":0.3154626447,"remaining_time":0.02855332553},
{"learn":[3.159425016],"iteration":917,"passed_time":0.3157072394,"remaining_time":0.02820042879},
{"learn":[3.159327058],"iteration":918,"passed_time":0.3159696266,"remaining_time":0.02784933597},
{"learn":[3.15819426],"iteration":919,"passed_time":0.3162138463,"remaining_time":0.0274968562},
{"learn":[3.157086603],"iteration":920,"passed_time":0.3164811921,"remaining_time":0.0271465952},
{"learn":[3.153354154],"iteration":921,"passed_time":0.3167168281,"remaining_time":0.02679383144},
{"learn":[3.153261317],"iteration":922,"passed_time":0.3169705482,"remaining_time":0.02644283013},
{"learn":[3.153168454],"iteration":923,"passed_time":0.317201809,"remaining_time":0.02609019208},
{"learn":[3.152080399],"iteration":924,"passed_time":0.3174269028,"remaining_time":0.02573731644},
{"learn":[3.151635144],"iteration":925,"passed_time":0.31768954,"remaining_time":0.02538771702},
{"learn":[3.147762655],"iteration":926,"passed_time":0.3179727199,"remaining_time":0.02503992292},
{"learn":[3.147172317],"iteration":927,"passed_time":0.3182019805,"remaining_time":0.0246880847},
{"learn":[3.146254125],"iteration":928,"passed_time":0.3184822019,"remaining_time":0.0243404051},
{"learn":[3.144869828],"iteration":929,"passed_time":0.3187360054,"remaining_time":0.02399088213},
{"learn":[3.143466218],"iteration":930,"passed_time":0.3190056846,"remaining_time":0.0236427414},
{"learn":[3.141919643],"iteration":931,"passed_time":0.319343742,"remaining_time":0.023299758},
{"learn":[3.141054135],"iteration":932,"passed_time":0.3197007586,"remaining_time":0.02295814666},
{"learn":[3.139390417],"iteration":933,"passed_time":0.3199479785,"remaining_time":0.02260874366},
{"learn":[3.139025283],"iteration":934,"passed_time":0.3202365336,"remaining_time":0.02226243282},
{"learn":[3.137824183],"iteration":935,"passed_time":0.3204848785,"remaining_time":0.02191349596},
{"learn":[3.135620453],"iteration":936,"passed_time":0.3207565161,"remaining_time":0.02156633993},
{"learn":[3.13443178],"iteration":937,"passed_time":0.3210291955,"remaining_time":0.02121941377},
{"learn":[3.132765713],"iteration":938,"passed_time":0.321312292,"remaining_time":0.02087332248},
{"learn":[3.131434124],"iteration":939,"passed_time":0.3215725125,"remaining_time":0.02052590505},
{"learn":[3.128384262],"iteration":940,"passed_time":0.3218527755,"remaining_time":0.0201799296},
{"learn":[3.128120455],"iteration":941,"passed_time":0.3221299551,"remaining_time":0.01983390382},
{"learn":[3.126314615],"iteration":942,"passed_time":0.3223940507,"remaining_time":0.01948723318},
{"learn":[3.125409666],"iteration":943,"passed_time":0.3226376454,"remaining_time":0.01913952134},
{"learn":[3.123072589],"iteration":944,"passed_time":0.3229138249,"remaining_time":0.01879392632},
{"learn":[3.122921099],"iteration":945,"passed_time":0.3231674617,"remaining_time":0.01844719126},
{"learn":[3.122182662],"iteration":946,"passed_time":0.3234498082,"remaining_time":0.01810225959},
{"learn":[3.120040951],"iteration":947,"passed_time":0.323754364,"remaining_time":0.0177586782},
{"learn":[3.118767799],"iteration":948,"passed_time":0.3240042923,"remaining_time":0.01741224332},
{"learn":[3.118203218],"iteration":949,"passed_time":0.3251136356,"remaining_time":0.01711124398},
{"learn":[3.116343362],"iteration":950,"passed_time":0.3253889818,"remaining_time":0.01676557319},
{"learn":[3.11480829],"iteration":951,"passed_time":0.3257181221,"remaining_time":0.01642276246},
{"learn":[3.112607903],"iteration":952,"passed_time":0.3259489245,"remaining_time":0.01607513059},
{"learn":[3.111661241],"iteration":953,"passed_time":0.3262453133,"remaining_time":0.01573090609},
{"learn":[3.110249676],"iteration":954,"passed_time":0.326525493,"remaining_time":0.015386018},
{"learn":[3.107333579],"iteration":955,"passed_time":0.3267546704,"remaining_time":0.01503891788},
{"learn":[3.107149851],"iteration":956,"passed_time":0.3270179326,"remaining_time":0.01469359572},
{"learn":[3.106867336],"iteration":957,"passed_time":0.3273341974,"remaining_time":0.01435076857},
{"learn":[3.10364681],"iteration":958,"passed_time":0.3276754632,"remaining_time":0.01400906569},
{"learn":[3.102703811],"iteration":959,"passed_time":0.3279782273,"remaining_time":0.01366575947},
{"learn":[3.101469264],"iteration":960,"passed_time":0.3282203636,"remaining_time":0.01332007719},
{"learn":[3.09863569],"iteration":961,"passed_time":0.3285200859,"remaining_time":0.01297688489},
{"learn":[3.09645939],"iteration":962,"passed_time":0.3287621388,"remaining_time":0.01263156712},
{"learn":[3.096240186],"iteration":963,"passed_time":0.3290989878,"remaining_time":0.0122900037},
{"learn":[3.094838828],"iteration":964,"passed_time":0.3293680837,"remaining_time":0.01194599267},
{"learn":[3.094176802],"iteration":965,"passed_time":0.3296708895,"remaining_time":0.01160332323},
{"learn":[3.093182279],"iteration":966,"passed_time":0.3299676116,"remaining_time":0.01126052863},
{"learn":[3.090150687],"iteration":967,"passed_time":0.3302528749,"remaining_time":0.01091745041},
{"learn":[3.088612829],"iteration":968,"passed_time":0.3305486387,"remaining_time":0.01057482745},
{"learn":[3.087153684],"iteration":969,"passed_time":0.3315221007,"remaining_time":0.01025326085},
{"learn":[3.085866843],"iteration":970,"passed_time":0.3317445693,"remaining_time":0.009907922256},
{"learn":[3.082669094],"iteration":971,"passed_time":0.3320269575,"remaining_time":0.009564562562},
{"learn":[3.081047548],"iteration":972,"passed_time":0.3322877196,"remaining_time":0.009220728088},
{"learn":[3.079684322],"iteration":973,"passed_time":0.3325413564,"remaining_time":0.008876873991},
{"learn":[3.07613431],"iteration":974,"passed_time":0.3328226612,"remaining_time":0.00853391439},
{"learn":[3.074005935],"iteration":975,"passed_time":0.3330921321,"remaining_time":0.008190790133},
{"learn":[3.072988853],"iteration":976,"passed_time":0.3334253559,"remaining_time":0.007849317489},
{"learn":[3.072344268],"iteration":977,"passed_time":0.3336832013,"remaining_time":0.007506166082},
{"learn":[3.070654438],"iteration":978,"passed_time":0.3340048829,"remaining_time":0.007164558265},
{"learn":[3.069724506],"iteration":979,"passed_time":0.3343011467,"remaining_time":0.006822472382},
{"learn":[3.067763166],"iteration":980,"passed_time":0.3346339539,"remaining_time":0.006481187689},
{"learn":[3.066737893],"iteration":981,"passed_time":0.3349250924,"remaining_time":0.00613915648},
{"learn":[3.065248174],"iteration":982,"passed_time":0.335223023,"remaining_time":0.005797346277},
{"learn":[3.063186837],"iteration":983,"passed_time":0.3355876649,"remaining_time":0.005456709999},
{"learn":[3.062880371],"iteration":984,"passed_time":0.3358709281,"remaining_time":0.005114785707},
{"learn":[3.061288645],"iteration":985,"passed_time":0.3361431491,"remaining_time":0.004772823618},
{"learn":[3.059970575],"iteration":986,"passed_time":0.3363932858,"remaining_time":0.004430711971},
{"learn":[3.059576341],"iteration":987,"passed_time":0.3366212547,"remaining_time":0.004088517264},
{"learn":[3.058175919],"iteration":988,"passed_time":0.3368878921,"remaining_time":0.003746983633},
{"learn":[3.056830702],"iteration":989,"passed_time":0.3371815308,"remaining_time":0.003405874048},
{"learn":[3.056336579],"iteration":990,"passed_time":0.3374741278,"remaining_time":0.003064850807},
{"learn":[3.055810414],"iteration":991,"passed_time":0.337743307,"remaining_time":0.002723736346},
{"learn":[3.055476518],"iteration":992,"passed_time":0.3380081943,"remaining_time":0.002382736516},
{"learn":[3.053331734],"iteration":993,"passed_time":0.3382372883,"remaining_time":0.002041673772},
{"learn":[3.050890374],"iteration":994,"passed_time":0.3384979671,"remaining_time":0.001700994809},
{"learn":[3.04972623],"iteration":995,"passed_time":0.3387682297,"remaining_time":0.001360514979},
{"learn":[3.047217327],"iteration":996,"passed_time":0.339048076,"remaining_time":0.001020204843},
{"learn":[3.047155483],"iteration":997,"passed_time":0.3392992127,"remaining_time":0.0006799583421},
{"learn":[3.04430671],"iteration":998,"passed_time":0.339577434,"remaining_time":0.0003399173514},
{"learn":[3.042664195],"iteration":999,"passed_time":0.3398242372,"remaining_time":0}
]}